[{"name":"const val AMBIGUOUS_OUTCOME: Int = 100","description":"com.jumio.sdk.retry.JumioRetryReasonIproov.AMBIGUOUS_OUTCOME","location":"jumio-iproov/com.jumio.sdk.retry/-jumio-retry-reason-iproov/-a-m-b-i-g-u-o-u-s_-o-u-t-c-o-m-e.html","searchKeys":["AMBIGUOUS_OUTCOME","const val AMBIGUOUS_OUTCOME: Int = 100","com.jumio.sdk.retry.JumioRetryReasonIproov.AMBIGUOUS_OUTCOME"]},{"name":"const val CAMERA: Int = 200","description":"com.jumio.sdk.retry.JumioRetryReasonIproov.CAMERA","location":"jumio-iproov/com.jumio.sdk.retry/-jumio-retry-reason-iproov/-c-a-m-e-r-a.html","searchKeys":["CAMERA","const val CAMERA: Int = 200","com.jumio.sdk.retry.JumioRetryReasonIproov.CAMERA"]},{"name":"const val CAMERA_PERMISSION: Int = 201","description":"com.jumio.sdk.retry.JumioRetryReasonIproov.CAMERA_PERMISSION","location":"jumio-iproov/com.jumio.sdk.retry/-jumio-retry-reason-iproov/-c-a-m-e-r-a_-p-e-r-m-i-s-s-i-o-n.html","searchKeys":["CAMERA_PERMISSION","const val CAMERA_PERMISSION: Int = 201","com.jumio.sdk.retry.JumioRetryReasonIproov.CAMERA_PERMISSION"]},{"name":"const val CAPTURE_ALREADY_ACTIVE: Int = 202","description":"com.jumio.sdk.retry.JumioRetryReasonIproov.CAPTURE_ALREADY_ACTIVE","location":"jumio-iproov/com.jumio.sdk.retry/-jumio-retry-reason-iproov/-c-a-p-t-u-r-e_-a-l-r-e-a-d-y_-a-c-t-i-v-e.html","searchKeys":["CAPTURE_ALREADY_ACTIVE","const val CAPTURE_ALREADY_ACTIVE: Int = 202","com.jumio.sdk.retry.JumioRetryReasonIproov.CAPTURE_ALREADY_ACTIVE"]},{"name":"const val FACE_DETECTOR: Int = 207","description":"com.jumio.sdk.retry.JumioRetryReasonIproov.FACE_DETECTOR","location":"jumio-iproov/com.jumio.sdk.retry/-jumio-retry-reason-iproov/-f-a-c-e_-d-e-t-e-c-t-o-r.html","searchKeys":["FACE_DETECTOR","const val FACE_DETECTOR: Int = 207","com.jumio.sdk.retry.JumioRetryReasonIproov.FACE_DETECTOR"]},{"name":"const val GENERIC_ERROR: Int = 209","description":"com.jumio.sdk.retry.JumioRetryReasonIproov.GENERIC_ERROR","location":"jumio-iproov/com.jumio.sdk.retry/-jumio-retry-reason-iproov/-g-e-n-e-r-i-c_-e-r-r-o-r.html","searchKeys":["GENERIC_ERROR","const val GENERIC_ERROR: Int = 209","com.jumio.sdk.retry.JumioRetryReasonIproov.GENERIC_ERROR"]},{"name":"const val GENERIC_FAILURE: Int = 107","description":"com.jumio.sdk.retry.JumioRetryReasonIproov.GENERIC_FAILURE","location":"jumio-iproov/com.jumio.sdk.retry/-jumio-retry-reason-iproov/-g-e-n-e-r-i-c_-f-a-i-l-u-r-e.html","searchKeys":["GENERIC_FAILURE","const val GENERIC_FAILURE: Int = 107","com.jumio.sdk.retry.JumioRetryReasonIproov.GENERIC_FAILURE"]},{"name":"const val LIGHTING_BACKLIT: Int = 103","description":"com.jumio.sdk.retry.JumioRetryReasonIproov.LIGHTING_BACKLIT","location":"jumio-iproov/com.jumio.sdk.retry/-jumio-retry-reason-iproov/-l-i-g-h-t-i-n-g_-b-a-c-k-l-i-t.html","searchKeys":["LIGHTING_BACKLIT","const val LIGHTING_BACKLIT: Int = 103","com.jumio.sdk.retry.JumioRetryReasonIproov.LIGHTING_BACKLIT"]},{"name":"const val LIGHTING_FLASH: Int = 102","description":"com.jumio.sdk.retry.JumioRetryReasonIproov.LIGHTING_FLASH","location":"jumio-iproov/com.jumio.sdk.retry/-jumio-retry-reason-iproov/-l-i-g-h-t-i-n-g_-f-l-a-s-h.html","searchKeys":["LIGHTING_FLASH","const val LIGHTING_FLASH: Int = 102","com.jumio.sdk.retry.JumioRetryReasonIproov.LIGHTING_FLASH"]},{"name":"const val LIGHTING_TOO_BRIGHT: Int = 105","description":"com.jumio.sdk.retry.JumioRetryReasonIproov.LIGHTING_TOO_BRIGHT","location":"jumio-iproov/com.jumio.sdk.retry/-jumio-retry-reason-iproov/-l-i-g-h-t-i-n-g_-t-o-o_-b-r-i-g-h-t.html","searchKeys":["LIGHTING_TOO_BRIGHT","const val LIGHTING_TOO_BRIGHT: Int = 105","com.jumio.sdk.retry.JumioRetryReasonIproov.LIGHTING_TOO_BRIGHT"]},{"name":"const val LIGHTING_TOO_DARK: Int = 104","description":"com.jumio.sdk.retry.JumioRetryReasonIproov.LIGHTING_TOO_DARK","location":"jumio-iproov/com.jumio.sdk.retry/-jumio-retry-reason-iproov/-l-i-g-h-t-i-n-g_-t-o-o_-d-a-r-k.html","searchKeys":["LIGHTING_TOO_DARK","const val LIGHTING_TOO_DARK: Int = 104","com.jumio.sdk.retry.JumioRetryReasonIproov.LIGHTING_TOO_DARK"]},{"name":"const val MOTION_MOUTH: Int = 106","description":"com.jumio.sdk.retry.JumioRetryReasonIproov.MOTION_MOUTH","location":"jumio-iproov/com.jumio.sdk.retry/-jumio-retry-reason-iproov/-m-o-t-i-o-n_-m-o-u-t-h.html","searchKeys":["MOTION_MOUTH","const val MOTION_MOUTH: Int = 106","com.jumio.sdk.retry.JumioRetryReasonIproov.MOTION_MOUTH"]},{"name":"const val MOTION_TOO_MUCH: Int = 101","description":"com.jumio.sdk.retry.JumioRetryReasonIproov.MOTION_TOO_MUCH","location":"jumio-iproov/com.jumio.sdk.retry/-jumio-retry-reason-iproov/-m-o-t-i-o-n_-t-o-o_-m-u-c-h.html","searchKeys":["MOTION_TOO_MUCH","const val MOTION_TOO_MUCH: Int = 101","com.jumio.sdk.retry.JumioRetryReasonIproov.MOTION_TOO_MUCH"]},{"name":"const val MULTI_WINDOW: Int = 208","description":"com.jumio.sdk.retry.JumioRetryReasonIproov.MULTI_WINDOW","location":"jumio-iproov/com.jumio.sdk.retry/-jumio-retry-reason-iproov/-m-u-l-t-i_-w-i-n-d-o-w.html","searchKeys":["MULTI_WINDOW","const val MULTI_WINDOW: Int = 208","com.jumio.sdk.retry.JumioRetryReasonIproov.MULTI_WINDOW"]},{"name":"const val NETWORK: Int = 205","description":"com.jumio.sdk.retry.JumioRetryReasonIproov.NETWORK","location":"jumio-iproov/com.jumio.sdk.retry/-jumio-retry-reason-iproov/-n-e-t-w-o-r-k.html","searchKeys":["NETWORK","const val NETWORK: Int = 205","com.jumio.sdk.retry.JumioRetryReasonIproov.NETWORK"]},{"name":"const val SERVER: Int = 204","description":"com.jumio.sdk.retry.JumioRetryReasonIproov.SERVER","location":"jumio-iproov/com.jumio.sdk.retry/-jumio-retry-reason-iproov/-s-e-r-v-e-r.html","searchKeys":["SERVER","const val SERVER: Int = 204","com.jumio.sdk.retry.JumioRetryReasonIproov.SERVER"]},{"name":"const val UNEXPECTED_ERROR: Int = 203","description":"com.jumio.sdk.retry.JumioRetryReasonIproov.UNEXPECTED_ERROR","location":"jumio-iproov/com.jumio.sdk.retry/-jumio-retry-reason-iproov/-u-n-e-x-p-e-c-t-e-d_-e-r-r-o-r.html","searchKeys":["UNEXPECTED_ERROR","const val UNEXPECTED_ERROR: Int = 203","com.jumio.sdk.retry.JumioRetryReasonIproov.UNEXPECTED_ERROR"]},{"name":"const val UNSUPPORTED_DEVICE: Int = 206","description":"com.jumio.sdk.retry.JumioRetryReasonIproov.UNSUPPORTED_DEVICE","location":"jumio-iproov/com.jumio.sdk.retry/-jumio-retry-reason-iproov/-u-n-s-u-p-p-o-r-t-e-d_-d-e-v-i-c-e.html","searchKeys":["UNSUPPORTED_DEVICE","const val UNSUPPORTED_DEVICE: Int = 206","com.jumio.sdk.retry.JumioRetryReasonIproov.UNSUPPORTED_DEVICE"]},{"name":"object JumioRetryReasonIproov","description":"com.jumio.sdk.retry.JumioRetryReasonIproov","location":"jumio-iproov/com.jumio.sdk.retry/-jumio-retry-reason-iproov/index.html","searchKeys":["JumioRetryReasonIproov","object JumioRetryReasonIproov","com.jumio.sdk.retry.JumioRetryReasonIproov"]},{"name":"const val NFC_BAC_ERROR: Int = 302","description":"com.jumio.sdk.retry.JumioRetryReasonNfc.NFC_BAC_ERROR","location":"jumio-nfc/com.jumio.sdk.retry/-jumio-retry-reason-nfc/-n-f-c_-b-a-c_-e-r-r-o-r.html","searchKeys":["NFC_BAC_ERROR","const val NFC_BAC_ERROR: Int = 302","com.jumio.sdk.retry.JumioRetryReasonNfc.NFC_BAC_ERROR"]},{"name":"const val NFC_DISABLED: Int = 301","description":"com.jumio.sdk.retry.JumioRetryReasonNfc.NFC_DISABLED","location":"jumio-nfc/com.jumio.sdk.retry/-jumio-retry-reason-nfc/-n-f-c_-d-i-s-a-b-l-e-d.html","searchKeys":["NFC_DISABLED","const val NFC_DISABLED: Int = 301","com.jumio.sdk.retry.JumioRetryReasonNfc.NFC_DISABLED"]},{"name":"const val NFC_TAG_LOST: Int = 303","description":"com.jumio.sdk.retry.JumioRetryReasonNfc.NFC_TAG_LOST","location":"jumio-nfc/com.jumio.sdk.retry/-jumio-retry-reason-nfc/-n-f-c_-t-a-g_-l-o-s-t.html","searchKeys":["NFC_TAG_LOST","const val NFC_TAG_LOST: Int = 303","com.jumio.sdk.retry.JumioRetryReasonNfc.NFC_TAG_LOST"]},{"name":"object JumioRetryReasonNfc","description":"com.jumio.sdk.retry.JumioRetryReasonNfc","location":"jumio-nfc/com.jumio.sdk.retry/-jumio-retry-reason-nfc/index.html","searchKeys":["JumioRetryReasonNfc","object JumioRetryReasonNfc","com.jumio.sdk.retry.JumioRetryReasonNfc"]},{"name":"ADDON_SCAN_PART()","description":"com.jumio.sdk.enums.JumioScanStep.ADDON_SCAN_PART","location":"jumio-core/com.jumio.sdk.enums/-jumio-scan-step/-a-d-d-o-n_-s-c-a-n_-p-a-r-t/index.html","searchKeys":["ADDON_SCAN_PART","ADDON_SCAN_PART()","com.jumio.sdk.enums.JumioScanStep.ADDON_SCAN_PART"]},{"name":"ATTACH_ACTIVITY()","description":"com.jumio.sdk.enums.JumioScanStep.ATTACH_ACTIVITY","location":"jumio-core/com.jumio.sdk.enums/-jumio-scan-step/-a-t-t-a-c-h_-a-c-t-i-v-i-t-y/index.html","searchKeys":["ATTACH_ACTIVITY","ATTACH_ACTIVITY()","com.jumio.sdk.enums.JumioScanStep.ATTACH_ACTIVITY"]},{"name":"BACK","description":"com.jumio.sdk.enums.JumioCameraFacing.BACK","location":"jumio-core/com.jumio.sdk.enums/-jumio-camera-facing/-b-a-c-k/index.html","searchKeys":["BACK","BACK","com.jumio.sdk.enums.JumioCameraFacing.BACK"]},{"name":"BACK()","description":"com.jumio.sdk.enums.JumioScanSide.BACK","location":"jumio-core/com.jumio.sdk.enums/-jumio-scan-side/-b-a-c-k/index.html","searchKeys":["BACK","BACK()","com.jumio.sdk.enums.JumioScanSide.BACK"]},{"name":"BARCODE()","description":"com.jumio.sdk.enums.JumioScanMode.BARCODE","location":"jumio-core/com.jumio.sdk.enums/-jumio-scan-mode/-b-a-r-c-o-d-e/index.html","searchKeys":["BARCODE","BARCODE()","com.jumio.sdk.enums.JumioScanMode.BARCODE"]},{"name":"CAMERA_AVAILABLE()","description":"com.jumio.sdk.enums.JumioScanUpdate.CAMERA_AVAILABLE","location":"jumio-core/com.jumio.sdk.enums/-jumio-scan-update/-c-a-m-e-r-a_-a-v-a-i-l-a-b-l-e/index.html","searchKeys":["CAMERA_AVAILABLE","CAMERA_AVAILABLE()","com.jumio.sdk.enums.JumioScanUpdate.CAMERA_AVAILABLE"]},{"name":"CAN_FINISH()","description":"com.jumio.sdk.enums.JumioScanStep.CAN_FINISH","location":"jumio-core/com.jumio.sdk.enums/-jumio-scan-step/-c-a-n_-f-i-n-i-s-h/index.html","searchKeys":["CAN_FINISH","CAN_FINISH()","com.jumio.sdk.enums.JumioScanStep.CAN_FINISH"]},{"name":"CONFIRMATION_VIEW()","description":"com.jumio.sdk.enums.JumioScanStep.CONFIRMATION_VIEW","location":"jumio-core/com.jumio.sdk.enums/-jumio-scan-step/-c-o-n-f-i-r-m-a-t-i-o-n_-v-i-e-w/index.html","searchKeys":["CONFIRMATION_VIEW","CONFIRMATION_VIEW()","com.jumio.sdk.enums.JumioScanStep.CONFIRMATION_VIEW"]},{"name":"DOCUMENT()","description":"com.jumio.sdk.credentials.JumioCredentialCategory.DOCUMENT","location":"jumio-core/com.jumio.sdk.credentials/-jumio-credential-category/-d-o-c-u-m-e-n-t/index.html","searchKeys":["DOCUMENT","DOCUMENT()","com.jumio.sdk.credentials.JumioCredentialCategory.DOCUMENT"]},{"name":"DOCUMENT()","description":"com.jumio.sdk.enums.JumioScanSide.DOCUMENT","location":"jumio-core/com.jumio.sdk.enums/-jumio-scan-side/-d-o-c-u-m-e-n-t/index.html","searchKeys":["DOCUMENT","DOCUMENT()","com.jumio.sdk.enums.JumioScanSide.DOCUMENT"]},{"name":"DRIVING_LICENSE()","description":"com.jumio.sdk.document.JumioDocumentType.DRIVING_LICENSE","location":"jumio-core/com.jumio.sdk.document/-jumio-document-type/-d-r-i-v-i-n-g_-l-i-c-e-n-s-e/index.html","searchKeys":["DRIVING_LICENSE","DRIVING_LICENSE()","com.jumio.sdk.document.JumioDocumentType.DRIVING_LICENSE"]},{"name":"EU","description":"com.jumio.sdk.enums.JumioDataCenter.EU","location":"jumio-core/com.jumio.sdk.enums/-jumio-data-center/-e-u/index.html","searchKeys":["EU","EU","com.jumio.sdk.enums.JumioDataCenter.EU"]},{"name":"FACE()","description":"com.jumio.sdk.credentials.JumioCredentialCategory.FACE","location":"jumio-core/com.jumio.sdk.credentials/-jumio-credential-category/-f-a-c-e/index.html","searchKeys":["FACE","FACE()","com.jumio.sdk.credentials.JumioCredentialCategory.FACE"]},{"name":"FACE()","description":"com.jumio.sdk.enums.JumioScanSide.FACE","location":"jumio-core/com.jumio.sdk.enums/-jumio-scan-side/-f-a-c-e/index.html","searchKeys":["FACE","FACE()","com.jumio.sdk.enums.JumioScanSide.FACE"]},{"name":"FACE_IPROOV()","description":"com.jumio.sdk.enums.JumioScanMode.FACE_IPROOV","location":"jumio-core/com.jumio.sdk.enums/-jumio-scan-mode/-f-a-c-e_-i-p-r-o-o-v/index.html","searchKeys":["FACE_IPROOV","FACE_IPROOV()","com.jumio.sdk.enums.JumioScanMode.FACE_IPROOV"]},{"name":"FACE_MANUAL()","description":"com.jumio.sdk.enums.JumioScanMode.FACE_MANUAL","location":"jumio-core/com.jumio.sdk.enums/-jumio-scan-mode/-f-a-c-e_-m-a-n-u-a-l/index.html","searchKeys":["FACE_MANUAL","FACE_MANUAL()","com.jumio.sdk.enums.JumioScanMode.FACE_MANUAL"]},{"name":"FALLBACK()","description":"com.jumio.sdk.enums.JumioScanUpdate.FALLBACK","location":"jumio-core/com.jumio.sdk.enums/-jumio-scan-update/-f-a-l-l-b-a-c-k/index.html","searchKeys":["FALLBACK","FALLBACK()","com.jumio.sdk.enums.JumioScanUpdate.FALLBACK"]},{"name":"FRONT","description":"com.jumio.sdk.enums.JumioCameraFacing.FRONT","location":"jumio-core/com.jumio.sdk.enums/-jumio-camera-facing/-f-r-o-n-t/index.html","searchKeys":["FRONT","FRONT","com.jumio.sdk.enums.JumioCameraFacing.FRONT"]},{"name":"FRONT()","description":"com.jumio.sdk.enums.JumioScanSide.FRONT","location":"jumio-core/com.jumio.sdk.enums/-jumio-scan-side/-f-r-o-n-t/index.html","searchKeys":["FRONT","FRONT()","com.jumio.sdk.enums.JumioScanSide.FRONT"]},{"name":"ID()","description":"com.jumio.sdk.credentials.JumioCredentialCategory.ID","location":"jumio-core/com.jumio.sdk.credentials/-jumio-credential-category/-i-d/index.html","searchKeys":["ID","ID()","com.jumio.sdk.credentials.JumioCredentialCategory.ID"]},{"name":"ID_CARD()","description":"com.jumio.sdk.document.JumioDocumentType.ID_CARD","location":"jumio-core/com.jumio.sdk.document/-jumio-document-type/-i-d_-c-a-r-d/index.html","searchKeys":["ID_CARD","ID_CARD()","com.jumio.sdk.document.JumioDocumentType.ID_CARD"]},{"name":"IMAGE_TAKEN()","description":"com.jumio.sdk.enums.JumioScanStep.IMAGE_TAKEN","location":"jumio-core/com.jumio.sdk.enums/-jumio-scan-step/-i-m-a-g-e_-t-a-k-e-n/index.html","searchKeys":["IMAGE_TAKEN","IMAGE_TAKEN()","com.jumio.sdk.enums.JumioScanStep.IMAGE_TAKEN"]},{"name":"LEGAL_HINT()","description":"com.jumio.sdk.enums.JumioScanUpdate.LEGAL_HINT","location":"jumio-core/com.jumio.sdk.enums/-jumio-scan-update/-l-e-g-a-l_-h-i-n-t/index.html","searchKeys":["LEGAL_HINT","LEGAL_HINT()","com.jumio.sdk.enums.JumioScanUpdate.LEGAL_HINT"]},{"name":"LINEFINDER()","description":"com.jumio.sdk.enums.JumioScanMode.LINEFINDER","location":"jumio-core/com.jumio.sdk.enums/-jumio-scan-mode/-l-i-n-e-f-i-n-d-e-r/index.html","searchKeys":["LINEFINDER","LINEFINDER()","com.jumio.sdk.enums.JumioScanMode.LINEFINDER"]},{"name":"MANUAL()","description":"com.jumio.sdk.enums.JumioScanMode.MANUAL","location":"jumio-core/com.jumio.sdk.enums/-jumio-scan-mode/-m-a-n-u-a-l/index.html","searchKeys":["MANUAL","MANUAL()","com.jumio.sdk.enums.JumioScanMode.MANUAL"]},{"name":"MRZ()","description":"com.jumio.sdk.enums.JumioScanMode.MRZ","location":"jumio-core/com.jumio.sdk.enums/-jumio-scan-mode/-m-r-z/index.html","searchKeys":["MRZ","MRZ()","com.jumio.sdk.enums.JumioScanMode.MRZ"]},{"name":"NFC()","description":"com.jumio.sdk.enums.JumioScanMode.NFC","location":"jumio-core/com.jumio.sdk.enums/-jumio-scan-mode/-n-f-c/index.html","searchKeys":["NFC","NFC()","com.jumio.sdk.enums.JumioScanMode.NFC"]},{"name":"NFC()","description":"com.jumio.sdk.enums.JumioScanSide.NFC","location":"jumio-core/com.jumio.sdk.enums/-jumio-scan-side/-n-f-c/index.html","searchKeys":["NFC","NFC()","com.jumio.sdk.enums.JumioScanSide.NFC"]},{"name":"NFC_EXTRACTION_FINISHED()","description":"com.jumio.sdk.enums.JumioScanUpdate.NFC_EXTRACTION_FINISHED","location":"jumio-core/com.jumio.sdk.enums/-jumio-scan-update/-n-f-c_-e-x-t-r-a-c-t-i-o-n_-f-i-n-i-s-h-e-d/index.html","searchKeys":["NFC_EXTRACTION_FINISHED","NFC_EXTRACTION_FINISHED()","com.jumio.sdk.enums.JumioScanUpdate.NFC_EXTRACTION_FINISHED"]},{"name":"NFC_EXTRACTION_PROGRESS()","description":"com.jumio.sdk.enums.JumioScanUpdate.NFC_EXTRACTION_PROGRESS","location":"jumio-core/com.jumio.sdk.enums/-jumio-scan-update/-n-f-c_-e-x-t-r-a-c-t-i-o-n_-p-r-o-g-r-e-s-s/index.html","searchKeys":["NFC_EXTRACTION_PROGRESS","NFC_EXTRACTION_PROGRESS()","com.jumio.sdk.enums.JumioScanUpdate.NFC_EXTRACTION_PROGRESS"]},{"name":"NFC_EXTRACTION_STARTED()","description":"com.jumio.sdk.enums.JumioScanUpdate.NFC_EXTRACTION_STARTED","location":"jumio-core/com.jumio.sdk.enums/-jumio-scan-update/-n-f-c_-e-x-t-r-a-c-t-i-o-n_-s-t-a-r-t-e-d/index.html","searchKeys":["NFC_EXTRACTION_STARTED","NFC_EXTRACTION_STARTED()","com.jumio.sdk.enums.JumioScanUpdate.NFC_EXTRACTION_STARTED"]},{"name":"PAPER()","description":"com.jumio.sdk.document.JumioDocumentVariant.PAPER","location":"jumio-core/com.jumio.sdk.document/-jumio-document-variant/-p-a-p-e-r/index.html","searchKeys":["PAPER","PAPER()","com.jumio.sdk.document.JumioDocumentVariant.PAPER"]},{"name":"PASSPORT()","description":"com.jumio.sdk.document.JumioDocumentType.PASSPORT","location":"jumio-core/com.jumio.sdk.document/-jumio-document-type/-p-a-s-s-p-o-r-t/index.html","searchKeys":["PASSPORT","PASSPORT()","com.jumio.sdk.document.JumioDocumentType.PASSPORT"]},{"name":"PLASTIC()","description":"com.jumio.sdk.document.JumioDocumentVariant.PLASTIC","location":"jumio-core/com.jumio.sdk.document/-jumio-document-variant/-p-l-a-s-t-i-c/index.html","searchKeys":["PLASTIC","PLASTIC()","com.jumio.sdk.document.JumioDocumentVariant.PLASTIC"]},{"name":"PREPARE()","description":"com.jumio.sdk.enums.JumioScanStep.PREPARE","location":"jumio-core/com.jumio.sdk.enums/-jumio-scan-step/-p-r-e-p-a-r-e/index.html","searchKeys":["PREPARE","PREPARE()","com.jumio.sdk.enums.JumioScanStep.PREPARE"]},{"name":"PROCESSING()","description":"com.jumio.sdk.enums.JumioScanStep.PROCESSING","location":"jumio-core/com.jumio.sdk.enums/-jumio-scan-step/-p-r-o-c-e-s-s-i-n-g/index.html","searchKeys":["PROCESSING","PROCESSING()","com.jumio.sdk.enums.JumioScanStep.PROCESSING"]},{"name":"REJECT_VIEW()","description":"com.jumio.sdk.enums.JumioScanStep.REJECT_VIEW","location":"jumio-core/com.jumio.sdk.enums/-jumio-scan-step/-r-e-j-e-c-t_-v-i-e-w/index.html","searchKeys":["REJECT_VIEW","REJECT_VIEW()","com.jumio.sdk.enums.JumioScanStep.REJECT_VIEW"]},{"name":"RETRY()","description":"com.jumio.sdk.enums.JumioScanStep.RETRY","location":"jumio-core/com.jumio.sdk.enums/-jumio-scan-step/-r-e-t-r-y/index.html","searchKeys":["RETRY","RETRY()","com.jumio.sdk.enums.JumioScanStep.RETRY"]},{"name":"SCAN_VIEW()","description":"com.jumio.sdk.enums.JumioScanStep.SCAN_VIEW","location":"jumio-core/com.jumio.sdk.enums/-jumio-scan-step/-s-c-a-n_-v-i-e-w/index.html","searchKeys":["SCAN_VIEW","SCAN_VIEW()","com.jumio.sdk.enums.JumioScanStep.SCAN_VIEW"]},{"name":"SG","description":"com.jumio.sdk.enums.JumioDataCenter.SG","location":"jumio-core/com.jumio.sdk.enums/-jumio-data-center/-s-g/index.html","searchKeys":["SG","SG","com.jumio.sdk.enums.JumioDataCenter.SG"]},{"name":"STARTED()","description":"com.jumio.sdk.enums.JumioScanStep.STARTED","location":"jumio-core/com.jumio.sdk.enums/-jumio-scan-step/-s-t-a-r-t-e-d/index.html","searchKeys":["STARTED","STARTED()","com.jumio.sdk.enums.JumioScanStep.STARTED"]},{"name":"US","description":"com.jumio.sdk.enums.JumioDataCenter.US","location":"jumio-core/com.jumio.sdk.enums/-jumio-data-center/-u-s/index.html","searchKeys":["US","US","com.jumio.sdk.enums.JumioDataCenter.US"]},{"name":"VISA()","description":"com.jumio.sdk.document.JumioDocumentType.VISA","location":"jumio-core/com.jumio.sdk.document/-jumio-document-type/-v-i-s-a/index.html","searchKeys":["VISA","VISA()","com.jumio.sdk.document.JumioDocumentType.VISA"]},{"name":"abstract class JumioCredential","description":"com.jumio.sdk.credentials.JumioCredential","location":"jumio-core/com.jumio.sdk.credentials/-jumio-credential/index.html","searchKeys":["JumioCredential","abstract class JumioCredential","com.jumio.sdk.credentials.JumioCredential"]},{"name":"abstract fun initScanPart(scanSide: JumioScanSide, scanPartInterface: JumioScanPartInterface): JumioScanPart","description":"com.jumio.sdk.credentials.JumioCredential.initScanPart","location":"jumio-core/com.jumio.sdk.credentials/-jumio-credential/init-scan-part.html","searchKeys":["initScanPart","abstract fun initScanPart(scanSide: JumioScanSide, scanPartInterface: JumioScanPartInterface): JumioScanPart","com.jumio.sdk.credentials.JumioCredential.initScanPart"]},{"name":"abstract fun onError(error: JumioError)","description":"com.jumio.sdk.interfaces.JumioControllerInterface.onError","location":"jumio-core/com.jumio.sdk.interfaces/-jumio-controller-interface/on-error.html","searchKeys":["onError","abstract fun onError(error: JumioError)","com.jumio.sdk.interfaces.JumioControllerInterface.onError"]},{"name":"abstract fun onFinished(result: JumioResult)","description":"com.jumio.sdk.interfaces.JumioControllerInterface.onFinished","location":"jumio-core/com.jumio.sdk.interfaces/-jumio-controller-interface/on-finished.html","searchKeys":["onFinished","abstract fun onFinished(result: JumioResult)","com.jumio.sdk.interfaces.JumioControllerInterface.onFinished"]},{"name":"abstract fun onInitialized(credentials: ArrayList<JumioCredentialInfo>, policyUrl: String?)","description":"com.jumio.sdk.interfaces.JumioControllerInterface.onInitialized","location":"jumio-core/com.jumio.sdk.interfaces/-jumio-controller-interface/on-initialized.html","searchKeys":["onInitialized","abstract fun onInitialized(credentials: ArrayList<JumioCredentialInfo>, policyUrl: String?)","com.jumio.sdk.interfaces.JumioControllerInterface.onInitialized"]},{"name":"abstract fun onScanStep(jumioScanStep: JumioScanStep, data: Any?)","description":"com.jumio.sdk.interfaces.JumioScanPartInterface.onScanStep","location":"jumio-core/com.jumio.sdk.interfaces/-jumio-scan-part-interface/on-scan-step.html","searchKeys":["onScanStep","abstract fun onScanStep(jumioScanStep: JumioScanStep, data: Any?)","com.jumio.sdk.interfaces.JumioScanPartInterface.onScanStep"]},{"name":"abstract fun onUpdate(jumioScanUpdate: JumioScanUpdate, data: Any?)","description":"com.jumio.sdk.interfaces.JumioScanPartInterface.onUpdate","location":"jumio-core/com.jumio.sdk.interfaces/-jumio-scan-part-interface/on-update.html","searchKeys":["onUpdate","abstract fun onUpdate(jumioScanUpdate: JumioScanUpdate, data: Any?)","com.jumio.sdk.interfaces.JumioScanPartInterface.onUpdate"]},{"name":"abstract val isConfigured: Boolean","description":"com.jumio.sdk.credentials.JumioCredential.isConfigured","location":"jumio-core/com.jumio.sdk.credentials/-jumio-credential/is-configured.html","searchKeys":["isConfigured","abstract val isConfigured: Boolean","com.jumio.sdk.credentials.JumioCredential.isConfigured"]},{"name":"class JumioActivityAttacher(activity: Activity)","description":"com.jumio.sdk.views.JumioActivityAttacher","location":"jumio-core/com.jumio.sdk.views/-jumio-activity-attacher/index.html","searchKeys":["JumioActivityAttacher","class JumioActivityAttacher(activity: Activity)","com.jumio.sdk.views.JumioActivityAttacher"]},{"name":"class JumioConfirmationView constructor(context: Context?, attrs: AttributeSet?, defStyleAttr: Int, cornerRadius: Int) : CheckView<ConfirmationInterface> ","description":"com.jumio.sdk.views.JumioConfirmationView","location":"jumio-core/com.jumio.sdk.views/-jumio-confirmation-view/index.html","searchKeys":["JumioConfirmationView","class JumioConfirmationView constructor(context: Context?, attrs: AttributeSet?, defStyleAttr: Int, cornerRadius: Int) : CheckView<ConfirmationInterface> ","com.jumio.sdk.views.JumioConfirmationView"]},{"name":"class JumioController","description":"com.jumio.sdk.controller.JumioController","location":"jumio-core/com.jumio.sdk.controller/-jumio-controller/index.html","searchKeys":["JumioController","class JumioController","com.jumio.sdk.controller.JumioController"]},{"name":"class JumioCredentialInfo(category: JumioCredentialCategory, id: String) : Serializable","description":"com.jumio.sdk.credentials.JumioCredentialInfo","location":"jumio-core/com.jumio.sdk.credentials/-jumio-credential-info/index.html","searchKeys":["JumioCredentialInfo","class JumioCredentialInfo(category: JumioCredentialCategory, id: String) : Serializable","com.jumio.sdk.credentials.JumioCredentialInfo"]},{"name":"class JumioDocument(type: JumioDocumentType, variant: JumioDocumentVariant) : Serializable","description":"com.jumio.sdk.document.JumioDocument","location":"jumio-core/com.jumio.sdk.document/-jumio-document/index.html","searchKeys":["JumioDocument","class JumioDocument(type: JumioDocumentType, variant: JumioDocumentVariant) : Serializable","com.jumio.sdk.document.JumioDocument"]},{"name":"class JumioError(isRetryable: Boolean, domain: String, code: String, message: String) : Serializable","description":"com.jumio.sdk.error.JumioError","location":"jumio-core/com.jumio.sdk.error/-jumio-error/index.html","searchKeys":["JumioError","class JumioError(isRetryable: Boolean, domain: String, code: String, message: String) : Serializable","com.jumio.sdk.error.JumioError"]},{"name":"class JumioFaceCredential : JumioCredential","description":"com.jumio.sdk.credentials.JumioFaceCredential","location":"jumio-core/com.jumio.sdk.credentials/-jumio-face-credential/index.html","searchKeys":["JumioFaceCredential","class JumioFaceCredential : JumioCredential","com.jumio.sdk.credentials.JumioFaceCredential"]},{"name":"class JumioFaceResult : JumioCredentialResult, Serializable","description":"com.jumio.sdk.result.JumioFaceResult","location":"jumio-core/com.jumio.sdk.result/-jumio-face-result/index.html","searchKeys":["JumioFaceResult","class JumioFaceResult : JumioCredentialResult, Serializable","com.jumio.sdk.result.JumioFaceResult"]},{"name":"class JumioIDCredential : JumioCredential","description":"com.jumio.sdk.credentials.JumioIDCredential","location":"jumio-core/com.jumio.sdk.credentials/-jumio-i-d-credential/index.html","searchKeys":["JumioIDCredential","class JumioIDCredential : JumioCredential","com.jumio.sdk.credentials.JumioIDCredential"]},{"name":"class JumioIDResult : JumioCredentialResult, Serializable","description":"com.jumio.sdk.result.JumioIDResult","location":"jumio-core/com.jumio.sdk.result/-jumio-i-d-result/index.html","searchKeys":["JumioIDResult","class JumioIDResult : JumioCredentialResult, Serializable","com.jumio.sdk.result.JumioIDResult"]},{"name":"class JumioImageData(authorizationModel: AuthorizationModel) : Serializable","description":"com.jumio.sdk.result.JumioImageData","location":"jumio-core/com.jumio.sdk.result/-jumio-image-data/index.html","searchKeys":["JumioImageData","class JumioImageData(authorizationModel: AuthorizationModel) : Serializable","com.jumio.sdk.result.JumioImageData"]},{"name":"class JumioRejectView constructor(context: Context?, attrs: AttributeSet?, defStyleAttr: Int, cornerRadius: Int) : CheckView<RejectInterface> ","description":"com.jumio.sdk.views.JumioRejectView","location":"jumio-core/com.jumio.sdk.views/-jumio-reject-view/index.html","searchKeys":["JumioRejectView","class JumioRejectView constructor(context: Context?, attrs: AttributeSet?, defStyleAttr: Int, cornerRadius: Int) : CheckView<RejectInterface> ","com.jumio.sdk.views.JumioRejectView"]},{"name":"class JumioResult : Serializable","description":"com.jumio.sdk.result.JumioResult","location":"jumio-core/com.jumio.sdk.result/-jumio-result/index.html","searchKeys":["JumioResult","class JumioResult : Serializable","com.jumio.sdk.result.JumioResult"]},{"name":"class JumioRetryReason(code: Int, message: String) : Serializable","description":"com.jumio.sdk.retry.JumioRetryReason","location":"jumio-core/com.jumio.sdk.retry/-jumio-retry-reason/index.html","searchKeys":["JumioRetryReason","class JumioRetryReason(code: Int, message: String) : Serializable","com.jumio.sdk.retry.JumioRetryReason"]},{"name":"class JumioSDK","description":"com.jumio.sdk.JumioSDK","location":"jumio-core/com.jumio.sdk/-jumio-s-d-k/index.html","searchKeys":["JumioSDK","class JumioSDK","com.jumio.sdk.JumioSDK"]},{"name":"class JumioScanPart : Serializable","description":"com.jumio.sdk.scanpart.JumioScanPart","location":"jumio-core/com.jumio.sdk.scanpart/-jumio-scan-part/index.html","searchKeys":["JumioScanPart","class JumioScanPart : Serializable","com.jumio.sdk.scanpart.JumioScanPart"]},{"name":"class JumioScanView constructor(context: Context?, attrs: AttributeSet?, defStyle: Int)","description":"com.jumio.sdk.views.JumioScanView","location":"jumio-core/com.jumio.sdk.views/-jumio-scan-view/index.html","searchKeys":["JumioScanView","class JumioScanView constructor(context: Context?, attrs: AttributeSet?, defStyle: Int)","com.jumio.sdk.views.JumioScanView"]},{"name":"const val ATTEMPT_FAILED: Int = 4","description":"com.jumio.sdk.retry.JumioRetryReasonGeneric.ATTEMPT_FAILED","location":"jumio-core/com.jumio.sdk.retry/-jumio-retry-reason-generic/-a-t-t-e-m-p-t_-f-a-i-l-e-d.html","searchKeys":["ATTEMPT_FAILED","const val ATTEMPT_FAILED: Int = 4","com.jumio.sdk.retry.JumioRetryReasonGeneric.ATTEMPT_FAILED"]},{"name":"const val BLACK_WHITE_COPY: String","description":"com.jumio.sdk.reject.JumioRejectReason.BLACK_WHITE_COPY","location":"jumio-core/com.jumio.sdk.reject/-jumio-reject-reason/-b-l-a-c-k_-w-h-i-t-e_-c-o-p-y.html","searchKeys":["BLACK_WHITE_COPY","const val BLACK_WHITE_COPY: String","com.jumio.sdk.reject.JumioRejectReason.BLACK_WHITE_COPY"]},{"name":"const val BLURRY: String","description":"com.jumio.sdk.reject.JumioRejectReason.BLURRY","location":"jumio-core/com.jumio.sdk.reject/-jumio-reject-reason/-b-l-u-r-r-y.html","searchKeys":["BLURRY","const val BLURRY: String","com.jumio.sdk.reject.JumioRejectReason.BLURRY"]},{"name":"const val COLOR_PHOTOCOPY: String","description":"com.jumio.sdk.reject.JumioRejectReason.COLOR_PHOTOCOPY","location":"jumio-core/com.jumio.sdk.reject/-jumio-reject-reason/-c-o-l-o-r_-p-h-o-t-o-c-o-p-y.html","searchKeys":["COLOR_PHOTOCOPY","const val COLOR_PHOTOCOPY: String","com.jumio.sdk.reject.JumioRejectReason.COLOR_PHOTOCOPY"]},{"name":"const val DAMAGED_DOCUMENT: String","description":"com.jumio.sdk.reject.JumioRejectReason.DAMAGED_DOCUMENT","location":"jumio-core/com.jumio.sdk.reject/-jumio-reject-reason/-d-a-m-a-g-e-d_-d-o-c-u-m-e-n-t.html","searchKeys":["DAMAGED_DOCUMENT","const val DAMAGED_DOCUMENT: String","com.jumio.sdk.reject.JumioRejectReason.DAMAGED_DOCUMENT"]},{"name":"const val DIGITAL_COPY: String","description":"com.jumio.sdk.reject.JumioRejectReason.DIGITAL_COPY","location":"jumio-core/com.jumio.sdk.reject/-jumio-reject-reason/-d-i-g-i-t-a-l_-c-o-p-y.html","searchKeys":["DIGITAL_COPY","const val DIGITAL_COPY: String","com.jumio.sdk.reject.JumioRejectReason.DIGITAL_COPY"]},{"name":"const val GENERIC: Int = 1","description":"com.jumio.sdk.retry.JumioRetryReasonGeneric.GENERIC","location":"jumio-core/com.jumio.sdk.retry/-jumio-retry-reason-generic/-g-e-n-e-r-i-c.html","searchKeys":["GENERIC","const val GENERIC: Int = 1","com.jumio.sdk.retry.JumioRetryReasonGeneric.GENERIC"]},{"name":"const val GLARE: String","description":"com.jumio.sdk.reject.JumioRejectReason.GLARE","location":"jumio-core/com.jumio.sdk.reject/-jumio-reject-reason/-g-l-a-r-e.html","searchKeys":["GLARE","const val GLARE: String","com.jumio.sdk.reject.JumioRejectReason.GLARE"]},{"name":"const val HIDDEN_PART_DOC: String","description":"com.jumio.sdk.reject.JumioRejectReason.HIDDEN_PART_DOC","location":"jumio-core/com.jumio.sdk.reject/-jumio-reject-reason/-h-i-d-d-e-n_-p-a-r-t_-d-o-c.html","searchKeys":["HIDDEN_PART_DOC","const val HIDDEN_PART_DOC: String","com.jumio.sdk.reject.JumioRejectReason.HIDDEN_PART_DOC"]},{"name":"const val MISSING_BACK: String","description":"com.jumio.sdk.reject.JumioRejectReason.MISSING_BACK","location":"jumio-core/com.jumio.sdk.reject/-jumio-reject-reason/-m-i-s-s-i-n-g_-b-a-c-k.html","searchKeys":["MISSING_BACK","const val MISSING_BACK: String","com.jumio.sdk.reject.JumioRejectReason.MISSING_BACK"]},{"name":"const val MISSING_FRONT: String","description":"com.jumio.sdk.reject.JumioRejectReason.MISSING_FRONT","location":"jumio-core/com.jumio.sdk.reject/-jumio-reject-reason/-m-i-s-s-i-n-g_-f-r-o-n-t.html","searchKeys":["MISSING_FRONT","const val MISSING_FRONT: String","com.jumio.sdk.reject.JumioRejectReason.MISSING_FRONT"]},{"name":"const val MISSING_PART_DOC: String","description":"com.jumio.sdk.reject.JumioRejectReason.MISSING_PART_DOC","location":"jumio-core/com.jumio.sdk.reject/-jumio-reject-reason/-m-i-s-s-i-n-g_-p-a-r-t_-d-o-c.html","searchKeys":["MISSING_PART_DOC","const val MISSING_PART_DOC: String","com.jumio.sdk.reject.JumioRejectReason.MISSING_PART_DOC"]},{"name":"const val MODE_FACE: Int = 1","description":"com.jumio.sdk.views.JumioScanView.Companion.MODE_FACE","location":"jumio-core/com.jumio.sdk.views/-jumio-scan-view/-companion/-m-o-d-e_-f-a-c-e.html","searchKeys":["MODE_FACE","const val MODE_FACE: Int = 1","com.jumio.sdk.views.JumioScanView.Companion.MODE_FACE"]},{"name":"const val MODE_ID: Int = 0","description":"com.jumio.sdk.views.JumioScanView.Companion.MODE_ID","location":"jumio-core/com.jumio.sdk.views/-jumio-scan-view/-companion/-m-o-d-e_-i-d.html","searchKeys":["MODE_ID","const val MODE_ID: Int = 0","com.jumio.sdk.views.JumioScanView.Companion.MODE_ID"]},{"name":"const val NOT_READABLE: String","description":"com.jumio.sdk.reject.JumioRejectReason.NOT_READABLE","location":"jumio-core/com.jumio.sdk.reject/-jumio-reject-reason/-n-o-t_-r-e-a-d-a-b-l-e.html","searchKeys":["NOT_READABLE","const val NOT_READABLE: String","com.jumio.sdk.reject.JumioRejectReason.NOT_READABLE"]},{"name":"const val NO_DOC: String","description":"com.jumio.sdk.reject.JumioRejectReason.NO_DOC","location":"jumio-core/com.jumio.sdk.reject/-jumio-reject-reason/-n-o_-d-o-c.html","searchKeys":["NO_DOC","const val NO_DOC: String","com.jumio.sdk.reject.JumioRejectReason.NO_DOC"]},{"name":"const val USER_BACK: Int = 3","description":"com.jumio.sdk.retry.JumioRetryReasonGeneric.USER_BACK","location":"jumio-core/com.jumio.sdk.retry/-jumio-retry-reason-generic/-u-s-e-r_-b-a-c-k.html","searchKeys":["USER_BACK","const val USER_BACK: Int = 3","com.jumio.sdk.retry.JumioRetryReasonGeneric.USER_BACK"]},{"name":"const val USER_CANCEL: Int = 2","description":"com.jumio.sdk.retry.JumioRetryReasonGeneric.USER_CANCEL","location":"jumio-core/com.jumio.sdk.retry/-jumio-retry-reason-generic/-u-s-e-r_-c-a-n-c-e-l.html","searchKeys":["USER_CANCEL","const val USER_CANCEL: Int = 2","com.jumio.sdk.retry.JumioRetryReasonGeneric.USER_CANCEL"]},{"name":"enum JumioCameraFacing","description":"com.jumio.sdk.enums.JumioCameraFacing","location":"jumio-core/com.jumio.sdk.enums/-jumio-camera-facing/index.html","searchKeys":["JumioCameraFacing","enum JumioCameraFacing","com.jumio.sdk.enums.JumioCameraFacing"]},{"name":"enum JumioCredentialCategory : Enum<JumioCredentialCategory> ","description":"com.jumio.sdk.credentials.JumioCredentialCategory","location":"jumio-core/com.jumio.sdk.credentials/-jumio-credential-category/index.html","searchKeys":["JumioCredentialCategory","enum JumioCredentialCategory : Enum<JumioCredentialCategory> ","com.jumio.sdk.credentials.JumioCredentialCategory"]},{"name":"enum JumioDataCenter","description":"com.jumio.sdk.enums.JumioDataCenter","location":"jumio-core/com.jumio.sdk.enums/-jumio-data-center/index.html","searchKeys":["JumioDataCenter","enum JumioDataCenter","com.jumio.sdk.enums.JumioDataCenter"]},{"name":"enum JumioDocumentType : Enum<JumioDocumentType> ","description":"com.jumio.sdk.document.JumioDocumentType","location":"jumio-core/com.jumio.sdk.document/-jumio-document-type/index.html","searchKeys":["JumioDocumentType","enum JumioDocumentType : Enum<JumioDocumentType> ","com.jumio.sdk.document.JumioDocumentType"]},{"name":"enum JumioDocumentVariant : Enum<JumioDocumentVariant> ","description":"com.jumio.sdk.document.JumioDocumentVariant","location":"jumio-core/com.jumio.sdk.document/-jumio-document-variant/index.html","searchKeys":["JumioDocumentVariant","enum JumioDocumentVariant : Enum<JumioDocumentVariant> ","com.jumio.sdk.document.JumioDocumentVariant"]},{"name":"enum JumioScanMode : Enum<JumioScanMode> ","description":"com.jumio.sdk.enums.JumioScanMode","location":"jumio-core/com.jumio.sdk.enums/-jumio-scan-mode/index.html","searchKeys":["JumioScanMode","enum JumioScanMode : Enum<JumioScanMode> ","com.jumio.sdk.enums.JumioScanMode"]},{"name":"enum JumioScanSide : Enum<JumioScanSide> ","description":"com.jumio.sdk.enums.JumioScanSide","location":"jumio-core/com.jumio.sdk.enums/-jumio-scan-side/index.html","searchKeys":["JumioScanSide","enum JumioScanSide : Enum<JumioScanSide> ","com.jumio.sdk.enums.JumioScanSide"]},{"name":"enum JumioScanStep : Enum<JumioScanStep> ","description":"com.jumio.sdk.enums.JumioScanStep","location":"jumio-core/com.jumio.sdk.enums/-jumio-scan-step/index.html","searchKeys":["JumioScanStep","enum JumioScanStep : Enum<JumioScanStep> ","com.jumio.sdk.enums.JumioScanStep"]},{"name":"enum JumioScanUpdate : Enum<JumioScanUpdate> ","description":"com.jumio.sdk.enums.JumioScanUpdate","location":"jumio-core/com.jumio.sdk.enums/-jumio-scan-update/index.html","searchKeys":["JumioScanUpdate","enum JumioScanUpdate : Enum<JumioScanUpdate> ","com.jumio.sdk.enums.JumioScanUpdate"]},{"name":"fun InterfaceImpl()","description":"com.jumio.sdk.views.JumioScanView.InterfaceImpl.InterfaceImpl","location":"jumio-core/com.jumio.sdk.views/-jumio-scan-view/-interface-impl/-interface-impl.html","searchKeys":["InterfaceImpl","fun InterfaceImpl()","com.jumio.sdk.views.JumioScanView.InterfaceImpl.InterfaceImpl"]},{"name":"fun JumioActivityAttacher(activity: Activity)","description":"com.jumio.sdk.views.JumioActivityAttacher.JumioActivityAttacher","location":"jumio-core/com.jumio.sdk.views/-jumio-activity-attacher/-jumio-activity-attacher.html","searchKeys":["JumioActivityAttacher","fun JumioActivityAttacher(activity: Activity)","com.jumio.sdk.views.JumioActivityAttacher.JumioActivityAttacher"]},{"name":"fun JumioConfirmationView(context: Context?, attrs: AttributeSet? = null, defStyleAttr: Int = 0, cornerRadius: Int = 0)","description":"com.jumio.sdk.views.JumioConfirmationView.JumioConfirmationView","location":"jumio-core/com.jumio.sdk.views/-jumio-confirmation-view/-jumio-confirmation-view.html","searchKeys":["JumioConfirmationView","fun JumioConfirmationView(context: Context?, attrs: AttributeSet? = null, defStyleAttr: Int = 0, cornerRadius: Int = 0)","com.jumio.sdk.views.JumioConfirmationView.JumioConfirmationView"]},{"name":"fun JumioCredentialInfo(category: JumioCredentialCategory, id: String)","description":"com.jumio.sdk.credentials.JumioCredentialInfo.JumioCredentialInfo","location":"jumio-core/com.jumio.sdk.credentials/-jumio-credential-info/-jumio-credential-info.html","searchKeys":["JumioCredentialInfo","fun JumioCredentialInfo(category: JumioCredentialCategory, id: String)","com.jumio.sdk.credentials.JumioCredentialInfo.JumioCredentialInfo"]},{"name":"fun JumioCredentialResult()","description":"com.jumio.sdk.result.JumioCredentialResult.JumioCredentialResult","location":"jumio-core/com.jumio.sdk.result/-jumio-credential-result/-jumio-credential-result.html","searchKeys":["JumioCredentialResult","fun JumioCredentialResult()","com.jumio.sdk.result.JumioCredentialResult.JumioCredentialResult"]},{"name":"fun JumioDocument(type: JumioDocumentType, variant: JumioDocumentVariant)","description":"com.jumio.sdk.document.JumioDocument.JumioDocument","location":"jumio-core/com.jumio.sdk.document/-jumio-document/-jumio-document.html","searchKeys":["JumioDocument","fun JumioDocument(type: JumioDocumentType, variant: JumioDocumentVariant)","com.jumio.sdk.document.JumioDocument.JumioDocument"]},{"name":"fun JumioError(isRetryable: Boolean, domain: String, code: String, message: String)","description":"com.jumio.sdk.error.JumioError.JumioError","location":"jumio-core/com.jumio.sdk.error/-jumio-error/-jumio-error.html","searchKeys":["JumioError","fun JumioError(isRetryable: Boolean, domain: String, code: String, message: String)","com.jumio.sdk.error.JumioError.JumioError"]},{"name":"fun JumioFaceResult()","description":"com.jumio.sdk.result.JumioFaceResult.JumioFaceResult","location":"jumio-core/com.jumio.sdk.result/-jumio-face-result/-jumio-face-result.html","searchKeys":["JumioFaceResult","fun JumioFaceResult()","com.jumio.sdk.result.JumioFaceResult.JumioFaceResult"]},{"name":"fun JumioIDResult()","description":"com.jumio.sdk.result.JumioIDResult.JumioIDResult","location":"jumio-core/com.jumio.sdk.result/-jumio-i-d-result/-jumio-i-d-result.html","searchKeys":["JumioIDResult","fun JumioIDResult()","com.jumio.sdk.result.JumioIDResult.JumioIDResult"]},{"name":"fun JumioImageData(authorizationModel: AuthorizationModel)","description":"com.jumio.sdk.result.JumioImageData.JumioImageData","location":"jumio-core/com.jumio.sdk.result/-jumio-image-data/-jumio-image-data.html","searchKeys":["JumioImageData","fun JumioImageData(authorizationModel: AuthorizationModel)","com.jumio.sdk.result.JumioImageData.JumioImageData"]},{"name":"fun JumioRejectView(context: Context?, attrs: AttributeSet? = null, defStyleAttr: Int = 0, cornerRadius: Int = 0)","description":"com.jumio.sdk.views.JumioRejectView.JumioRejectView","location":"jumio-core/com.jumio.sdk.views/-jumio-reject-view/-jumio-reject-view.html","searchKeys":["JumioRejectView","fun JumioRejectView(context: Context?, attrs: AttributeSet? = null, defStyleAttr: Int = 0, cornerRadius: Int = 0)","com.jumio.sdk.views.JumioRejectView.JumioRejectView"]},{"name":"fun JumioRetryReason(code: Int, message: String)","description":"com.jumio.sdk.retry.JumioRetryReason.JumioRetryReason","location":"jumio-core/com.jumio.sdk.retry/-jumio-retry-reason/-jumio-retry-reason.html","searchKeys":["JumioRetryReason","fun JumioRetryReason(code: Int, message: String)","com.jumio.sdk.retry.JumioRetryReason.JumioRetryReason"]},{"name":"fun JumioSDK(context: Context)","description":"com.jumio.sdk.JumioSDK.JumioSDK","location":"jumio-core/com.jumio.sdk/-jumio-s-d-k/-jumio-s-d-k.html","searchKeys":["JumioSDK","fun JumioSDK(context: Context)","com.jumio.sdk.JumioSDK.JumioSDK"]},{"name":"fun JumioScanView(context: Context?, attrs: AttributeSet? = null, defStyle: Int = 0)","description":"com.jumio.sdk.views.JumioScanView.JumioScanView","location":"jumio-core/com.jumio.sdk.views/-jumio-scan-view/-jumio-scan-view.html","searchKeys":["JumioScanView","fun JumioScanView(context: Context?, attrs: AttributeSet? = null, defStyle: Int = 0)","com.jumio.sdk.views.JumioScanView.JumioScanView"]},{"name":"fun attach(scanPart: JumioScanPart)","description":"com.jumio.sdk.views.JumioActivityAttacher.attach","location":"jumio-core/com.jumio.sdk.views/-jumio-activity-attacher/attach.html","searchKeys":["attach","fun attach(scanPart: JumioScanPart)","com.jumio.sdk.views.JumioActivityAttacher.attach"]},{"name":"fun cancel()","description":"com.jumio.sdk.controller.JumioController.cancel","location":"jumio-core/com.jumio.sdk.controller/-jumio-controller/cancel.html","searchKeys":["cancel","fun cancel()","com.jumio.sdk.controller.JumioController.cancel"]},{"name":"fun cancel()","description":"com.jumio.sdk.scanpart.JumioScanPart.cancel","location":"jumio-core/com.jumio.sdk.scanpart/-jumio-scan-part/cancel.html","searchKeys":["cancel","fun cancel()","com.jumio.sdk.scanpart.JumioScanPart.cancel"]},{"name":"fun clear()","description":"com.jumio.sdk.result.JumioImageData.clear","location":"jumio-core/com.jumio.sdk.result/-jumio-image-data/clear.html","searchKeys":["clear","fun clear()","com.jumio.sdk.result.JumioImageData.clear"]},{"name":"fun confirm()","description":"com.jumio.sdk.views.JumioConfirmationView.confirm","location":"jumio-core/com.jumio.sdk.views/-jumio-confirmation-view/confirm.html","searchKeys":["confirm","fun confirm()","com.jumio.sdk.views.JumioConfirmationView.confirm"]},{"name":"fun convertToAlpha2(alpha3Code: String?): String?","description":"com.jumio.sdk.util.IsoCountryConverter.convertToAlpha2","location":"jumio-core/com.jumio.sdk.util/-iso-country-converter/convert-to-alpha2.html","searchKeys":["convertToAlpha2","fun convertToAlpha2(alpha3Code: String?): String?","com.jumio.sdk.util.IsoCountryConverter.convertToAlpha2"]},{"name":"fun convertToAlpha3(alpha2Code: String?): String?","description":"com.jumio.sdk.util.IsoCountryConverter.convertToAlpha3","location":"jumio-core/com.jumio.sdk.util/-iso-country-converter/convert-to-alpha3.html","searchKeys":["convertToAlpha3","fun convertToAlpha3(alpha2Code: String?): String?","com.jumio.sdk.util.IsoCountryConverter.convertToAlpha3"]},{"name":"fun fallback()","description":"com.jumio.sdk.scanpart.JumioScanPart.fallback","location":"jumio-core/com.jumio.sdk.scanpart/-jumio-scan-part/fallback.html","searchKeys":["fallback","fun fallback()","com.jumio.sdk.scanpart.JumioScanPart.fallback"]},{"name":"fun finish()","description":"com.jumio.sdk.controller.JumioController.finish","location":"jumio-core/com.jumio.sdk.controller/-jumio-controller/finish.html","searchKeys":["finish","fun finish()","com.jumio.sdk.controller.JumioController.finish"]},{"name":"fun finish()","description":"com.jumio.sdk.scanpart.JumioScanPart.finish","location":"jumio-core/com.jumio.sdk.scanpart/-jumio-scan-part/finish.html","searchKeys":["finish","fun finish()","com.jumio.sdk.scanpart.JumioScanPart.finish"]},{"name":"fun fromLocalizedName(localizedDocument: String, c: Context): JumioDocumentType?","description":"com.jumio.sdk.document.JumioDocumentType.Companion.fromLocalizedName","location":"jumio-core/com.jumio.sdk.document/-jumio-document-type/-companion/from-localized-name.html","searchKeys":["fromLocalizedName","fun fromLocalizedName(localizedDocument: String, c: Context): JumioDocumentType?","com.jumio.sdk.document.JumioDocumentType.Companion.fromLocalizedName"]},{"name":"fun fromString(id: String): JumioDocumentType?","description":"com.jumio.sdk.document.JumioDocumentType.Companion.fromString","location":"jumio-core/com.jumio.sdk.document/-jumio-document-type/-companion/from-string.html","searchKeys":["fromString","fun fromString(id: String): JumioDocumentType?","com.jumio.sdk.document.JumioDocumentType.Companion.fromString"]},{"name":"fun getAddonPart(): JumioScanPart?","description":"com.jumio.sdk.credentials.JumioCredential.getAddonPart","location":"jumio-core/com.jumio.sdk.credentials/-jumio-credential/get-addon-part.html","searchKeys":["getAddonPart","fun getAddonPart(): JumioScanPart?","com.jumio.sdk.credentials.JumioCredential.getAddonPart"]},{"name":"fun getBitmap(scanSide: JumioScanSide): Bitmap?","description":"com.jumio.sdk.result.JumioImageData.getBitmap","location":"jumio-core/com.jumio.sdk.result/-jumio-image-data/get-bitmap.html","searchKeys":["getBitmap","fun getBitmap(scanSide: JumioScanSide): Bitmap?","com.jumio.sdk.result.JumioImageData.getBitmap"]},{"name":"fun getByteArray(scanSide: JumioScanSide): ByteArray?","description":"com.jumio.sdk.result.JumioImageData.getByteArray","location":"jumio-core/com.jumio.sdk.result/-jumio-image-data/get-byte-array.html","searchKeys":["getByteArray","fun getByteArray(scanSide: JumioScanSide): ByteArray?","com.jumio.sdk.result.JumioImageData.getByteArray"]},{"name":"fun getFaceResult(credentialInfo: JumioCredentialInfo): JumioFaceResult?","description":"com.jumio.sdk.result.JumioResult.getFaceResult","location":"jumio-core/com.jumio.sdk.result/-jumio-result/get-face-result.html","searchKeys":["getFaceResult","fun getFaceResult(credentialInfo: JumioCredentialInfo): JumioFaceResult?","com.jumio.sdk.result.JumioResult.getFaceResult"]},{"name":"fun getHelpAnimation(animationView: JumioAnimationView)","description":"com.jumio.sdk.scanpart.JumioScanPart.getHelpAnimation","location":"jumio-core/com.jumio.sdk.scanpart/-jumio-scan-part/get-help-animation.html","searchKeys":["getHelpAnimation","fun getHelpAnimation(animationView: JumioAnimationView)","com.jumio.sdk.scanpart.JumioScanPart.getHelpAnimation"]},{"name":"fun getIDResult(credentialInfo: JumioCredentialInfo): JumioIDResult?","description":"com.jumio.sdk.result.JumioResult.getIDResult","location":"jumio-core/com.jumio.sdk.result/-jumio-result/get-i-d-result.html","searchKeys":["getIDResult","fun getIDResult(credentialInfo: JumioCredentialInfo): JumioIDResult?","com.jumio.sdk.result.JumioResult.getIDResult"]},{"name":"fun getLocalizedName(c: Context): String","description":"com.jumio.sdk.document.JumioDocumentType.getLocalizedName","location":"jumio-core/com.jumio.sdk.document/-jumio-document-type/get-localized-name.html","searchKeys":["getLocalizedName","fun getLocalizedName(c: Context): String","com.jumio.sdk.document.JumioDocumentType.getLocalizedName"]},{"name":"fun getMissingPermissions(context: Context): Array<String?>","description":"com.jumio.sdk.JumioSDK.Companion.getMissingPermissions","location":"jumio-core/com.jumio.sdk/-jumio-s-d-k/-companion/get-missing-permissions.html","searchKeys":["getMissingPermissions","fun getMissingPermissions(context: Context): Array<String?>","com.jumio.sdk.JumioSDK.Companion.getMissingPermissions"]},{"name":"fun getResult(credentialInfo: JumioCredentialInfo): JumioCredentialResult?","description":"com.jumio.sdk.result.JumioResult.getResult","location":"jumio-core/com.jumio.sdk.result/-jumio-result/get-result.html","searchKeys":["getResult","fun getResult(credentialInfo: JumioCredentialInfo): JumioCredentialResult?","com.jumio.sdk.result.JumioResult.getResult"]},{"name":"fun giveDataDogConsent(boolean: Boolean)","description":"com.jumio.sdk.JumioSDK.Companion.giveDataDogConsent","location":"jumio-core/com.jumio.sdk/-jumio-s-d-k/-companion/give-data-dog-consent.html","searchKeys":["giveDataDogConsent","fun giveDataDogConsent(boolean: Boolean)","com.jumio.sdk.JumioSDK.Companion.giveDataDogConsent"]},{"name":"fun hasAllRequiredPermissions(context: Context): Boolean","description":"com.jumio.sdk.JumioSDK.Companion.hasAllRequiredPermissions","location":"jumio-core/com.jumio.sdk/-jumio-s-d-k/-companion/has-all-required-permissions.html","searchKeys":["hasAllRequiredPermissions","fun hasAllRequiredPermissions(context: Context): Boolean","com.jumio.sdk.JumioSDK.Companion.hasAllRequiredPermissions"]},{"name":"fun hasPermissionsFor(context: Context, names: Array<String>): Boolean","description":"com.jumio.sdk.JumioSDK.Companion.hasPermissionsFor","location":"jumio-core/com.jumio.sdk/-jumio-s-d-k/-companion/has-permissions-for.html","searchKeys":["hasPermissionsFor","fun hasPermissionsFor(context: Context, names: Array<String>): Boolean","com.jumio.sdk.JumioSDK.Companion.hasPermissionsFor"]},{"name":"fun hasSide(scanSide: JumioScanSide): Boolean","description":"com.jumio.sdk.result.JumioImageData.hasSide","location":"jumio-core/com.jumio.sdk.result/-jumio-image-data/has-side.html","searchKeys":["hasSide","fun hasSide(scanSide: JumioScanSide): Boolean","com.jumio.sdk.result.JumioImageData.hasSide"]},{"name":"fun initScanPart(scanPartInterface: JumioScanPartInterface): JumioScanPart","description":"com.jumio.sdk.credentials.JumioFaceCredential.initScanPart","location":"jumio-core/com.jumio.sdk.credentials/-jumio-face-credential/init-scan-part.html","searchKeys":["initScanPart","fun initScanPart(scanPartInterface: JumioScanPartInterface): JumioScanPart","com.jumio.sdk.credentials.JumioFaceCredential.initScanPart"]},{"name":"fun isRooted(context: Context): Boolean","description":"com.jumio.sdk.JumioSDK.Companion.isRooted","location":"jumio-core/com.jumio.sdk/-jumio-s-d-k/-companion/is-rooted.html","searchKeys":["isRooted","fun isRooted(context: Context): Boolean","com.jumio.sdk.JumioSDK.Companion.isRooted"]},{"name":"fun isSupportedConfiguration(country: String, document: JumioDocument): Boolean","description":"com.jumio.sdk.credentials.JumioIDCredential.isSupportedConfiguration","location":"jumio-core/com.jumio.sdk.credentials/-jumio-i-d-credential/is-supported-configuration.html","searchKeys":["isSupportedConfiguration","fun isSupportedConfiguration(country: String, document: JumioDocument): Boolean","com.jumio.sdk.credentials.JumioIDCredential.isSupportedConfiguration"]},{"name":"fun isSupportedPlatform(context: Context): Boolean","description":"com.jumio.sdk.JumioSDK.Companion.isSupportedPlatform","location":"jumio-core/com.jumio.sdk/-jumio-s-d-k/-companion/is-supported-platform.html","searchKeys":["isSupportedPlatform","fun isSupportedPlatform(context: Context): Boolean","com.jumio.sdk.JumioSDK.Companion.isSupportedPlatform"]},{"name":"fun isTablet(context: Context): Boolean","description":"com.jumio.sdk.JumioSDK.Companion.isTablet","location":"jumio-core/com.jumio.sdk/-jumio-s-d-k/-companion/is-tablet.html","searchKeys":["isTablet","fun isTablet(context: Context): Boolean","com.jumio.sdk.JumioSDK.Companion.isTablet"]},{"name":"fun persist(data: Bundle)","description":"com.jumio.sdk.controller.JumioController.persist","location":"jumio-core/com.jumio.sdk.controller/-jumio-controller/persist.html","searchKeys":["persist","fun persist(data: Bundle)","com.jumio.sdk.controller.JumioController.persist"]},{"name":"fun restore(context: Context, data: Bundle, controllerInterface: JumioControllerInterface, scanPartInterface: JumioScanPartInterface?, restore: (controller: JumioController, ArrayList<JumioCredentialInfo>, activeCredential: JumioCredential?, activeScanPart: JumioScanPart?) -> Unit)","description":"com.jumio.sdk.JumioSDK.restore","location":"jumio-core/com.jumio.sdk/-jumio-s-d-k/restore.html","searchKeys":["restore","fun restore(context: Context, data: Bundle, controllerInterface: JumioControllerInterface, scanPartInterface: JumioScanPartInterface?, restore: (controller: JumioController, ArrayList<JumioCredentialInfo>, activeCredential: JumioCredential?, activeScanPart: JumioScanPart?) -> Unit)","com.jumio.sdk.JumioSDK.restore"]},{"name":"fun retake()","description":"com.jumio.sdk.views.JumioConfirmationView.retake","location":"jumio-core/com.jumio.sdk.views/-jumio-confirmation-view/retake.html","searchKeys":["retake","fun retake()","com.jumio.sdk.views.JumioConfirmationView.retake"]},{"name":"fun retake()","description":"com.jumio.sdk.views.JumioRejectView.retake","location":"jumio-core/com.jumio.sdk.views/-jumio-reject-view/retake.html","searchKeys":["retake","fun retake()","com.jumio.sdk.views.JumioRejectView.retake"]},{"name":"fun retry(error: JumioError)","description":"com.jumio.sdk.controller.JumioController.retry","location":"jumio-core/com.jumio.sdk.controller/-jumio-controller/retry.html","searchKeys":["retry","fun retry(error: JumioError)","com.jumio.sdk.controller.JumioController.retry"]},{"name":"fun retry(reason: JumioRetryReason)","description":"com.jumio.sdk.scanpart.JumioScanPart.retry","location":"jumio-core/com.jumio.sdk.scanpart/-jumio-scan-part/retry.html","searchKeys":["retry","fun retry(reason: JumioRetryReason)","com.jumio.sdk.scanpart.JumioScanPart.retry"]},{"name":"fun setConfiguration(country: String, document: JumioDocument)","description":"com.jumio.sdk.credentials.JumioIDCredential.setConfiguration","location":"jumio-core/com.jumio.sdk.credentials/-jumio-i-d-credential/set-configuration.html","searchKeys":["setConfiguration","fun setConfiguration(country: String, document: JumioDocument)","com.jumio.sdk.credentials.JumioIDCredential.setConfiguration"]},{"name":"fun start()","description":"com.jumio.sdk.scanpart.JumioScanPart.start","location":"jumio-core/com.jumio.sdk.scanpart/-jumio-scan-part/start.html","searchKeys":["start","fun start()","com.jumio.sdk.scanpart.JumioScanPart.start"]},{"name":"fun start(context: Context, controllerInterface: JumioControllerInterface): JumioController","description":"com.jumio.sdk.JumioSDK.start","location":"jumio-core/com.jumio.sdk/-jumio-s-d-k/start.html","searchKeys":["start","fun start(context: Context, controllerInterface: JumioControllerInterface): JumioController","com.jumio.sdk.JumioSDK.start"]},{"name":"fun start(credentialInfo: JumioCredentialInfo): JumioCredential","description":"com.jumio.sdk.controller.JumioController.start","location":"jumio-core/com.jumio.sdk.controller/-jumio-controller/start.html","searchKeys":["start","fun start(credentialInfo: JumioCredentialInfo): JumioCredential","com.jumio.sdk.controller.JumioController.start"]},{"name":"fun stop()","description":"com.jumio.sdk.controller.JumioController.stop","location":"jumio-core/com.jumio.sdk.controller/-jumio-controller/stop.html","searchKeys":["stop","fun stop()","com.jumio.sdk.controller.JumioController.stop"]},{"name":"fun userConsented()","description":"com.jumio.sdk.controller.JumioController.userConsented","location":"jumio-core/com.jumio.sdk.controller/-jumio-controller/user-consented.html","searchKeys":["userConsented","fun userConsented()","com.jumio.sdk.controller.JumioController.userConsented"]},{"name":"inner class InterfaceImpl : ViewTreeObserver.OnGlobalLayoutListener","description":"com.jumio.sdk.views.JumioScanView.InterfaceImpl","location":"jumio-core/com.jumio.sdk.views/-jumio-scan-view/-interface-impl/index.html","searchKeys":["InterfaceImpl","inner class InterfaceImpl : ViewTreeObserver.OnGlobalLayoutListener","com.jumio.sdk.views.JumioScanView.InterfaceImpl"]},{"name":"interface JumioControllerInterface","description":"com.jumio.sdk.interfaces.JumioControllerInterface","location":"jumio-core/com.jumio.sdk.interfaces/-jumio-controller-interface/index.html","searchKeys":["JumioControllerInterface","interface JumioControllerInterface","com.jumio.sdk.interfaces.JumioControllerInterface"]},{"name":"interface JumioScanPartInterface","description":"com.jumio.sdk.interfaces.JumioScanPartInterface","location":"jumio-core/com.jumio.sdk.interfaces/-jumio-scan-part-interface/index.html","searchKeys":["JumioScanPartInterface","interface JumioScanPartInterface","com.jumio.sdk.interfaces.JumioScanPartInterface"]},{"name":"object Companion","description":"com.jumio.sdk.JumioSDK.Companion","location":"jumio-core/com.jumio.sdk/-jumio-s-d-k/-companion/index.html","searchKeys":["Companion","object Companion","com.jumio.sdk.JumioSDK.Companion"]},{"name":"object Companion","description":"com.jumio.sdk.controller.JumioController.Companion","location":"jumio-core/com.jumio.sdk.controller/-jumio-controller/-companion/index.html","searchKeys":["Companion","object Companion","com.jumio.sdk.controller.JumioController.Companion"]},{"name":"object Companion","description":"com.jumio.sdk.document.JumioDocumentType.Companion","location":"jumio-core/com.jumio.sdk.document/-jumio-document-type/-companion/index.html","searchKeys":["Companion","object Companion","com.jumio.sdk.document.JumioDocumentType.Companion"]},{"name":"object Companion","description":"com.jumio.sdk.scanpart.JumioScanPart.Companion","location":"jumio-core/com.jumio.sdk.scanpart/-jumio-scan-part/-companion/index.html","searchKeys":["Companion","object Companion","com.jumio.sdk.scanpart.JumioScanPart.Companion"]},{"name":"object Companion","description":"com.jumio.sdk.views.JumioScanView.Companion","location":"jumio-core/com.jumio.sdk.views/-jumio-scan-view/-companion/index.html","searchKeys":["Companion","object Companion","com.jumio.sdk.views.JumioScanView.Companion"]},{"name":"object IsoCountryConverter","description":"com.jumio.sdk.util.IsoCountryConverter","location":"jumio-core/com.jumio.sdk.util/-iso-country-converter/index.html","searchKeys":["IsoCountryConverter","object IsoCountryConverter","com.jumio.sdk.util.IsoCountryConverter"]},{"name":"object JumioRejectReason","description":"com.jumio.sdk.reject.JumioRejectReason","location":"jumio-core/com.jumio.sdk.reject/-jumio-reject-reason/index.html","searchKeys":["JumioRejectReason","object JumioRejectReason","com.jumio.sdk.reject.JumioRejectReason"]},{"name":"object JumioRetryReasonGeneric","description":"com.jumio.sdk.retry.JumioRetryReasonGeneric","location":"jumio-core/com.jumio.sdk.retry/-jumio-retry-reason-generic/index.html","searchKeys":["JumioRetryReasonGeneric","object JumioRetryReasonGeneric","com.jumio.sdk.retry.JumioRetryReasonGeneric"]},{"name":"open class JumioAnimationView : RelativeLayout","description":"com.jumio.sdk.views.JumioAnimationView","location":"jumio-core/com.jumio.sdk.views/-jumio-animation-view/index.html","searchKeys":["JumioAnimationView","open class JumioAnimationView : RelativeLayout","com.jumio.sdk.views.JumioAnimationView"]},{"name":"open class JumioCredentialResult : Serializable","description":"com.jumio.sdk.result.JumioCredentialResult","location":"jumio-core/com.jumio.sdk.result/-jumio-credential-result/index.html","searchKeys":["JumioCredentialResult","open class JumioCredentialResult : Serializable","com.jumio.sdk.result.JumioCredentialResult"]},{"name":"open class MissingPermissionException : Exception","description":"com.jumio.sdk.exceptions.MissingPermissionException","location":"jumio-core/com.jumio.sdk.exceptions/-missing-permission-exception/index.html","searchKeys":["MissingPermissionException","open class MissingPermissionException : Exception","com.jumio.sdk.exceptions.MissingPermissionException"]},{"name":"open class PlatformNotSupportedException : Exception","description":"com.jumio.sdk.exceptions.PlatformNotSupportedException","location":"jumio-core/com.jumio.sdk.exceptions/-platform-not-supported-exception/index.html","searchKeys":["PlatformNotSupportedException","open class PlatformNotSupportedException : Exception","com.jumio.sdk.exceptions.PlatformNotSupportedException"]},{"name":"open class SDKNotConfiguredException : Exception","description":"com.jumio.sdk.exceptions.SDKNotConfiguredException","location":"jumio-core/com.jumio.sdk.exceptions/-s-d-k-not-configured-exception/index.html","searchKeys":["SDKNotConfiguredException","open class SDKNotConfiguredException : Exception","com.jumio.sdk.exceptions.SDKNotConfiguredException"]},{"name":"open fun JumioAnimationView(context: Context)","description":"com.jumio.sdk.views.JumioAnimationView.JumioAnimationView","location":"jumio-core/com.jumio.sdk.views/-jumio-animation-view/-jumio-animation-view.html","searchKeys":["JumioAnimationView","open fun JumioAnimationView(context: Context)","com.jumio.sdk.views.JumioAnimationView.JumioAnimationView"]},{"name":"open fun JumioAnimationView(context: Context, attrs: AttributeSet)","description":"com.jumio.sdk.views.JumioAnimationView.JumioAnimationView","location":"jumio-core/com.jumio.sdk.views/-jumio-animation-view/-jumio-animation-view.html","searchKeys":["JumioAnimationView","open fun JumioAnimationView(context: Context, attrs: AttributeSet)","com.jumio.sdk.views.JumioAnimationView.JumioAnimationView"]},{"name":"open fun JumioAnimationView(context: Context, attrs: AttributeSet, defStyle: Int)","description":"com.jumio.sdk.views.JumioAnimationView.JumioAnimationView","location":"jumio-core/com.jumio.sdk.views/-jumio-animation-view/-jumio-animation-view.html","searchKeys":["JumioAnimationView","open fun JumioAnimationView(context: Context, attrs: AttributeSet, defStyle: Int)","com.jumio.sdk.views.JumioAnimationView.JumioAnimationView"]},{"name":"open fun MissingPermissionException(permission: String)","description":"com.jumio.sdk.exceptions.MissingPermissionException.MissingPermissionException","location":"jumio-core/com.jumio.sdk.exceptions/-missing-permission-exception/-missing-permission-exception.html","searchKeys":["MissingPermissionException","open fun MissingPermissionException(permission: String)","com.jumio.sdk.exceptions.MissingPermissionException.MissingPermissionException"]},{"name":"open fun MissingPermissionException(whichPermissions: Array<String>)","description":"com.jumio.sdk.exceptions.MissingPermissionException.MissingPermissionException","location":"jumio-core/com.jumio.sdk.exceptions/-missing-permission-exception/-missing-permission-exception.html","searchKeys":["MissingPermissionException","open fun MissingPermissionException(whichPermissions: Array<String>)","com.jumio.sdk.exceptions.MissingPermissionException.MissingPermissionException"]},{"name":"open fun PlatformNotSupportedException()","description":"com.jumio.sdk.exceptions.PlatformNotSupportedException.PlatformNotSupportedException","location":"jumio-core/com.jumio.sdk.exceptions/-platform-not-supported-exception/-platform-not-supported-exception.html","searchKeys":["PlatformNotSupportedException","open fun PlatformNotSupportedException()","com.jumio.sdk.exceptions.PlatformNotSupportedException.PlatformNotSupportedException"]},{"name":"open fun PlatformNotSupportedException(detailMessage: String)","description":"com.jumio.sdk.exceptions.PlatformNotSupportedException.PlatformNotSupportedException","location":"jumio-core/com.jumio.sdk.exceptions/-platform-not-supported-exception/-platform-not-supported-exception.html","searchKeys":["PlatformNotSupportedException","open fun PlatformNotSupportedException(detailMessage: String)","com.jumio.sdk.exceptions.PlatformNotSupportedException.PlatformNotSupportedException"]},{"name":"open fun PlatformNotSupportedException(detailMessage: String, throwable: Throwable)","description":"com.jumio.sdk.exceptions.PlatformNotSupportedException.PlatformNotSupportedException","location":"jumio-core/com.jumio.sdk.exceptions/-platform-not-supported-exception/-platform-not-supported-exception.html","searchKeys":["PlatformNotSupportedException","open fun PlatformNotSupportedException(detailMessage: String, throwable: Throwable)","com.jumio.sdk.exceptions.PlatformNotSupportedException.PlatformNotSupportedException"]},{"name":"open fun PlatformNotSupportedException(throwable: Throwable)","description":"com.jumio.sdk.exceptions.PlatformNotSupportedException.PlatformNotSupportedException","location":"jumio-core/com.jumio.sdk.exceptions/-platform-not-supported-exception/-platform-not-supported-exception.html","searchKeys":["PlatformNotSupportedException","open fun PlatformNotSupportedException(throwable: Throwable)","com.jumio.sdk.exceptions.PlatformNotSupportedException.PlatformNotSupportedException"]},{"name":"open fun SDKNotConfiguredException()","description":"com.jumio.sdk.exceptions.SDKNotConfiguredException.SDKNotConfiguredException","location":"jumio-core/com.jumio.sdk.exceptions/-s-d-k-not-configured-exception/-s-d-k-not-configured-exception.html","searchKeys":["SDKNotConfiguredException","open fun SDKNotConfiguredException()","com.jumio.sdk.exceptions.SDKNotConfiguredException.SDKNotConfiguredException"]},{"name":"open fun SDKNotConfiguredException(detailMessage: String)","description":"com.jumio.sdk.exceptions.SDKNotConfiguredException.SDKNotConfiguredException","location":"jumio-core/com.jumio.sdk.exceptions/-s-d-k-not-configured-exception/-s-d-k-not-configured-exception.html","searchKeys":["SDKNotConfiguredException","open fun SDKNotConfiguredException(detailMessage: String)","com.jumio.sdk.exceptions.SDKNotConfiguredException.SDKNotConfiguredException"]},{"name":"open fun SDKNotConfiguredException(detailMessage: String, throwable: Throwable)","description":"com.jumio.sdk.exceptions.SDKNotConfiguredException.SDKNotConfiguredException","location":"jumio-core/com.jumio.sdk.exceptions/-s-d-k-not-configured-exception/-s-d-k-not-configured-exception.html","searchKeys":["SDKNotConfiguredException","open fun SDKNotConfiguredException(detailMessage: String, throwable: Throwable)","com.jumio.sdk.exceptions.SDKNotConfiguredException.SDKNotConfiguredException"]},{"name":"open fun SDKNotConfiguredException(throwable: Throwable)","description":"com.jumio.sdk.exceptions.SDKNotConfiguredException.SDKNotConfiguredException","location":"jumio-core/com.jumio.sdk.exceptions/-s-d-k-not-configured-exception/-s-d-k-not-configured-exception.html","searchKeys":["SDKNotConfiguredException","open fun SDKNotConfiguredException(throwable: Throwable)","com.jumio.sdk.exceptions.SDKNotConfiguredException.SDKNotConfiguredException"]},{"name":"open fun attach(scanPart: JumioScanPart)","description":"com.jumio.sdk.views.JumioScanView.attach","location":"jumio-core/com.jumio.sdk.views/-jumio-scan-view/attach.html","searchKeys":["attach","open fun attach(scanPart: JumioScanPart)","com.jumio.sdk.views.JumioScanView.attach"]},{"name":"open fun cancel()","description":"com.jumio.sdk.credentials.JumioCredential.cancel","location":"jumio-core/com.jumio.sdk.credentials/-jumio-credential/cancel.html","searchKeys":["cancel","open fun cancel()","com.jumio.sdk.credentials.JumioCredential.cancel"]},{"name":"open fun destroy()","description":"com.jumio.sdk.views.JumioAnimationView.destroy","location":"jumio-core/com.jumio.sdk.views/-jumio-animation-view/destroy.html","searchKeys":["destroy","open fun destroy()","com.jumio.sdk.views.JumioAnimationView.destroy"]},{"name":"open fun finish()","description":"com.jumio.sdk.credentials.JumioCredential.finish","location":"jumio-core/com.jumio.sdk.credentials/-jumio-credential/finish.html","searchKeys":["finish","open fun finish()","com.jumio.sdk.credentials.JumioCredential.finish"]},{"name":"open fun getPermissions(): Array<String>","description":"com.jumio.sdk.exceptions.MissingPermissionException.getPermissions","location":"jumio-core/com.jumio.sdk.exceptions/-missing-permission-exception/get-permissions.html","searchKeys":["getPermissions","open fun getPermissions(): Array<String>","com.jumio.sdk.exceptions.MissingPermissionException.getPermissions"]},{"name":"open fun pause(): <ERROR CLASS>","description":"com.jumio.sdk.views.JumioScanView.pause","location":"jumio-core/com.jumio.sdk.views/-jumio-scan-view/pause.html","searchKeys":["pause","open fun pause(): <ERROR CLASS>","com.jumio.sdk.views.JumioScanView.pause"]},{"name":"open fun resume(): <ERROR CLASS>","description":"com.jumio.sdk.views.JumioScanView.resume","location":"jumio-core/com.jumio.sdk.views/-jumio-scan-view/resume.html","searchKeys":["resume","open fun resume(): <ERROR CLASS>","com.jumio.sdk.views.JumioScanView.resume"]},{"name":"open fun switchCamera(): <ERROR CLASS>","description":"com.jumio.sdk.views.JumioScanView.switchCamera","location":"jumio-core/com.jumio.sdk.views/-jumio-scan-view/switch-camera.html","searchKeys":["switchCamera","open fun switchCamera(): <ERROR CLASS>","com.jumio.sdk.views.JumioScanView.switchCamera"]},{"name":"open fun takePicture(): <ERROR CLASS>","description":"com.jumio.sdk.views.JumioScanView.takePicture","location":"jumio-core/com.jumio.sdk.views/-jumio-scan-view/take-picture.html","searchKeys":["takePicture","open fun takePicture(): <ERROR CLASS>","com.jumio.sdk.views.JumioScanView.takePicture"]},{"name":"open fun valueOf(name: String): JumioCameraFacing","description":"com.jumio.sdk.enums.JumioCameraFacing.valueOf","location":"jumio-core/com.jumio.sdk.enums/-jumio-camera-facing/value-of.html","searchKeys":["valueOf","open fun valueOf(name: String): JumioCameraFacing","com.jumio.sdk.enums.JumioCameraFacing.valueOf"]},{"name":"open fun valueOf(name: String): JumioDataCenter","description":"com.jumio.sdk.enums.JumioDataCenter.valueOf","location":"jumio-core/com.jumio.sdk.enums/-jumio-data-center/value-of.html","searchKeys":["valueOf","open fun valueOf(name: String): JumioDataCenter","com.jumio.sdk.enums.JumioDataCenter.valueOf"]},{"name":"open fun values(): Array<JumioCameraFacing>","description":"com.jumio.sdk.enums.JumioCameraFacing.values","location":"jumio-core/com.jumio.sdk.enums/-jumio-camera-facing/values.html","searchKeys":["values","open fun values(): Array<JumioCameraFacing>","com.jumio.sdk.enums.JumioCameraFacing.values"]},{"name":"open fun values(): Array<JumioDataCenter>","description":"com.jumio.sdk.enums.JumioDataCenter.values","location":"jumio-core/com.jumio.sdk.enums/-jumio-data-center/values.html","searchKeys":["values","open fun values(): Array<JumioDataCenter>","com.jumio.sdk.enums.JumioDataCenter.values"]},{"name":"open override fun cancel()","description":"com.jumio.sdk.credentials.JumioIDCredential.cancel","location":"jumio-core/com.jumio.sdk.credentials/-jumio-i-d-credential/cancel.html","searchKeys":["cancel","open override fun cancel()","com.jumio.sdk.credentials.JumioIDCredential.cancel"]},{"name":"open override fun initScanPart(scanSide: JumioScanSide, scanPartInterface: JumioScanPartInterface): JumioScanPart","description":"com.jumio.sdk.credentials.JumioFaceCredential.initScanPart","location":"jumio-core/com.jumio.sdk.credentials/-jumio-face-credential/init-scan-part.html","searchKeys":["initScanPart","open override fun initScanPart(scanSide: JumioScanSide, scanPartInterface: JumioScanPartInterface): JumioScanPart","com.jumio.sdk.credentials.JumioFaceCredential.initScanPart"]},{"name":"open override fun initScanPart(scanSide: JumioScanSide, scanPartInterface: JumioScanPartInterface): JumioScanPart","description":"com.jumio.sdk.credentials.JumioIDCredential.initScanPart","location":"jumio-core/com.jumio.sdk.credentials/-jumio-i-d-credential/init-scan-part.html","searchKeys":["initScanPart","open override fun initScanPart(scanSide: JumioScanSide, scanPartInterface: JumioScanPartInterface): JumioScanPart","com.jumio.sdk.credentials.JumioIDCredential.initScanPart"]},{"name":"open override fun onGlobalLayout()","description":"com.jumio.sdk.views.JumioScanView.InterfaceImpl.onGlobalLayout","location":"jumio-core/com.jumio.sdk.views/-jumio-scan-view/-interface-impl/on-global-layout.html","searchKeys":["onGlobalLayout","open override fun onGlobalLayout()","com.jumio.sdk.views.JumioScanView.InterfaceImpl.onGlobalLayout"]},{"name":"open override fun toString(): String","description":"com.jumio.sdk.document.JumioDocument.toString","location":"jumio-core/com.jumio.sdk.document/-jumio-document/to-string.html","searchKeys":["toString","open override fun toString(): String","com.jumio.sdk.document.JumioDocument.toString"]},{"name":"open override fun toString(): String","description":"com.jumio.sdk.document.JumioDocumentType.toString","location":"jumio-core/com.jumio.sdk.document/-jumio-document-type/to-string.html","searchKeys":["toString","open override fun toString(): String","com.jumio.sdk.document.JumioDocumentType.toString"]},{"name":"open override val isConfigured: Boolean","description":"com.jumio.sdk.credentials.JumioFaceCredential.isConfigured","location":"jumio-core/com.jumio.sdk.credentials/-jumio-face-credential/is-configured.html","searchKeys":["isConfigured","open override val isConfigured: Boolean","com.jumio.sdk.credentials.JumioFaceCredential.isConfigured"]},{"name":"open override val isConfigured: Boolean","description":"com.jumio.sdk.credentials.JumioIDCredential.isConfigured","location":"jumio-core/com.jumio.sdk.credentials/-jumio-i-d-credential/is-configured.html","searchKeys":["isConfigured","open override val isConfigured: Boolean","com.jumio.sdk.credentials.JumioIDCredential.isConfigured"]},{"name":"open val hasFlash: Boolean","description":"com.jumio.sdk.views.JumioScanView.hasFlash","location":"jumio-core/com.jumio.sdk.views/-jumio-scan-view/has-flash.html","searchKeys":["hasFlash","open val hasFlash: Boolean","com.jumio.sdk.views.JumioScanView.hasFlash"]},{"name":"open val hasMultipleCameras: Boolean","description":"com.jumio.sdk.views.JumioScanView.hasMultipleCameras","location":"jumio-core/com.jumio.sdk.views/-jumio-scan-view/has-multiple-cameras.html","searchKeys":["hasMultipleCameras","open val hasMultipleCameras: Boolean","com.jumio.sdk.views.JumioScanView.hasMultipleCameras"]},{"name":"open val isShutterEnabled: Boolean","description":"com.jumio.sdk.views.JumioScanView.isShutterEnabled","location":"jumio-core/com.jumio.sdk.views/-jumio-scan-view/is-shutter-enabled.html","searchKeys":["isShutterEnabled","open val isShutterEnabled: Boolean","com.jumio.sdk.views.JumioScanView.isShutterEnabled"]},{"name":"open val minRatio: Float","description":"com.jumio.sdk.views.JumioScanView.minRatio","location":"jumio-core/com.jumio.sdk.views/-jumio-scan-view/min-ratio.html","searchKeys":["minRatio","open val minRatio: Float","com.jumio.sdk.views.JumioScanView.minRatio"]},{"name":"open var cameraFacing: JumioCameraFacing","description":"com.jumio.sdk.views.JumioScanView.cameraFacing","location":"jumio-core/com.jumio.sdk.views/-jumio-scan-view/camera-facing.html","searchKeys":["cameraFacing","open var cameraFacing: JumioCameraFacing","com.jumio.sdk.views.JumioScanView.cameraFacing"]},{"name":"open var extraction: Boolean","description":"com.jumio.sdk.views.JumioScanView.extraction","location":"jumio-core/com.jumio.sdk.views/-jumio-scan-view/extraction.html","searchKeys":["extraction","open var extraction: Boolean","com.jumio.sdk.views.JumioScanView.extraction"]},{"name":"open var flash: Boolean","description":"com.jumio.sdk.views.JumioScanView.flash","location":"jumio-core/com.jumio.sdk.views/-jumio-scan-view/flash.html","searchKeys":["flash","open var flash: Boolean","com.jumio.sdk.views.JumioScanView.flash"]},{"name":"open var ratio: Float","description":"com.jumio.sdk.views.JumioScanView.ratio","location":"jumio-core/com.jumio.sdk.views/-jumio-scan-view/ratio.html","searchKeys":["ratio","open var ratio: Float","com.jumio.sdk.views.JumioScanView.ratio"]},{"name":"val accountId: String?","description":"com.jumio.sdk.result.JumioResult.accountId","location":"jumio-core/com.jumio.sdk.result/-jumio-result/account-id.html","searchKeys":["accountId","val accountId: String?","com.jumio.sdk.result.JumioResult.accountId"]},{"name":"val activity: Activity","description":"com.jumio.sdk.views.JumioActivityAttacher.activity","location":"jumio-core/com.jumio.sdk.views/-jumio-activity-attacher/activity.html","searchKeys":["activity","val activity: Activity","com.jumio.sdk.views.JumioActivityAttacher.activity"]},{"name":"val category: JumioCredentialCategory","description":"com.jumio.sdk.credentials.JumioCredentialInfo.category","location":"jumio-core/com.jumio.sdk.credentials/-jumio-credential-info/category.html","searchKeys":["category","val category: JumioCredentialCategory","com.jumio.sdk.credentials.JumioCredentialInfo.category"]},{"name":"val code: Int","description":"com.jumio.sdk.retry.JumioRetryReason.code","location":"jumio-core/com.jumio.sdk.retry/-jumio-retry-reason/code.html","searchKeys":["code","val code: Int","com.jumio.sdk.retry.JumioRetryReason.code"]},{"name":"val code: String","description":"com.jumio.sdk.error.JumioError.code","location":"jumio-core/com.jumio.sdk.error/-jumio-error/code.html","searchKeys":["code","val code: String","com.jumio.sdk.error.JumioError.code"]},{"name":"val countries: Map<String, List<JumioDocument>>","description":"com.jumio.sdk.credentials.JumioIDCredential.countries","location":"jumio-core/com.jumio.sdk.credentials/-jumio-i-d-credential/countries.html","searchKeys":["countries","val countries: Map<String, List<JumioDocument>>","com.jumio.sdk.credentials.JumioIDCredential.countries"]},{"name":"val credentialInfos: ArrayList<JumioCredentialInfo>? = null","description":"com.jumio.sdk.result.JumioResult.credentialInfos","location":"jumio-core/com.jumio.sdk.result/-jumio-result/credential-infos.html","searchKeys":["credentialInfos","val credentialInfos: ArrayList<JumioCredentialInfo>? = null","com.jumio.sdk.result.JumioResult.credentialInfos"]},{"name":"val domain: String","description":"com.jumio.sdk.error.JumioError.domain","location":"jumio-core/com.jumio.sdk.error/-jumio-error/domain.html","searchKeys":["domain","val domain: String","com.jumio.sdk.error.JumioError.domain"]},{"name":"val error: JumioError? = null","description":"com.jumio.sdk.result.JumioResult.error","location":"jumio-core/com.jumio.sdk.result/-jumio-result/error.html","searchKeys":["error","val error: JumioError? = null","com.jumio.sdk.result.JumioResult.error"]},{"name":"val hasFallback: Boolean","description":"com.jumio.sdk.scanpart.JumioScanPart.hasFallback","location":"jumio-core/com.jumio.sdk.scanpart/-jumio-scan-part/has-fallback.html","searchKeys":["hasFallback","val hasFallback: Boolean","com.jumio.sdk.scanpart.JumioScanPart.hasFallback"]},{"name":"val id: String","description":"com.jumio.sdk.credentials.JumioCredentialInfo.id","location":"jumio-core/com.jumio.sdk.credentials/-jumio-credential-info/id.html","searchKeys":["id","val id: String","com.jumio.sdk.credentials.JumioCredentialInfo.id"]},{"name":"val isComplete: Boolean","description":"com.jumio.sdk.controller.JumioController.isComplete","location":"jumio-core/com.jumio.sdk.controller/-jumio-controller/is-complete.html","searchKeys":["isComplete","val isComplete: Boolean","com.jumio.sdk.controller.JumioController.isComplete"]},{"name":"val isComplete: Boolean","description":"com.jumio.sdk.credentials.JumioCredential.isComplete","location":"jumio-core/com.jumio.sdk.credentials/-jumio-credential/is-complete.html","searchKeys":["isComplete","val isComplete: Boolean","com.jumio.sdk.credentials.JumioCredential.isComplete"]},{"name":"val isRetryable: Boolean","description":"com.jumio.sdk.error.JumioError.isRetryable","location":"jumio-core/com.jumio.sdk.error/-jumio-error/is-retryable.html","searchKeys":["isRetryable","val isRetryable: Boolean","com.jumio.sdk.error.JumioError.isRetryable"]},{"name":"val isSuccess: Boolean","description":"com.jumio.sdk.result.JumioResult.isSuccess","location":"jumio-core/com.jumio.sdk.result/-jumio-result/is-success.html","searchKeys":["isSuccess","val isSuccess: Boolean","com.jumio.sdk.result.JumioResult.isSuccess"]},{"name":"val message: String","description":"com.jumio.sdk.error.JumioError.message","location":"jumio-core/com.jumio.sdk.error/-jumio-error/message.html","searchKeys":["message","val message: String","com.jumio.sdk.error.JumioError.message"]},{"name":"val message: String","description":"com.jumio.sdk.retry.JumioRetryReason.message","location":"jumio-core/com.jumio.sdk.retry/-jumio-retry-reason/message.html","searchKeys":["message","val message: String","com.jumio.sdk.retry.JumioRetryReason.message"]},{"name":"val requiredPermissions: Array<String>","description":"com.jumio.sdk.JumioSDK.Companion.requiredPermissions","location":"jumio-core/com.jumio.sdk/-jumio-s-d-k/-companion/required-permissions.html","searchKeys":["requiredPermissions","val requiredPermissions: Array<String>","com.jumio.sdk.JumioSDK.Companion.requiredPermissions"]},{"name":"val scanMode: JumioScanMode","description":"com.jumio.sdk.scanpart.JumioScanPart.scanMode","location":"jumio-core/com.jumio.sdk.scanpart/-jumio-scan-part/scan-mode.html","searchKeys":["scanMode","val scanMode: JumioScanMode","com.jumio.sdk.scanpart.JumioScanPart.scanMode"]},{"name":"val scanSides: ArrayList<JumioScanSide>","description":"com.jumio.sdk.credentials.JumioCredential.scanSides","location":"jumio-core/com.jumio.sdk.credentials/-jumio-credential/scan-sides.html","searchKeys":["scanSides","val scanSides: ArrayList<JumioScanSide>","com.jumio.sdk.credentials.JumioCredential.scanSides"]},{"name":"val suggestedCountry: String?","description":"com.jumio.sdk.credentials.JumioIDCredential.suggestedCountry","location":"jumio-core/com.jumio.sdk.credentials/-jumio-i-d-credential/suggested-country.html","searchKeys":["suggestedCountry","val suggestedCountry: String?","com.jumio.sdk.credentials.JumioIDCredential.suggestedCountry"]},{"name":"val type: JumioDocumentType","description":"com.jumio.sdk.document.JumioDocument.type","location":"jumio-core/com.jumio.sdk.document/-jumio-document/type.html","searchKeys":["type","val type: JumioDocumentType","com.jumio.sdk.document.JumioDocument.type"]},{"name":"val variant: JumioDocumentVariant","description":"com.jumio.sdk.document.JumioDocument.variant","location":"jumio-core/com.jumio.sdk.document/-jumio-document/variant.html","searchKeys":["variant","val variant: JumioDocumentVariant","com.jumio.sdk.document.JumioDocument.variant"]},{"name":"val version: String","description":"com.jumio.sdk.JumioSDK.Companion.version","location":"jumio-core/com.jumio.sdk/-jumio-s-d-k/-companion/version.html","searchKeys":["version","val version: String","com.jumio.sdk.JumioSDK.Companion.version"]},{"name":"val workflowExecutionId: String?","description":"com.jumio.sdk.result.JumioResult.workflowExecutionId","location":"jumio-core/com.jumio.sdk.result/-jumio-result/workflow-execution-id.html","searchKeys":["workflowExecutionId","val workflowExecutionId: String?","com.jumio.sdk.result.JumioResult.workflowExecutionId"]},{"name":"var address: String? = null","description":"com.jumio.sdk.result.JumioIDResult.address","location":"jumio-core/com.jumio.sdk.result/-jumio-i-d-result/address.html","searchKeys":["address","var address: String? = null","com.jumio.sdk.result.JumioIDResult.address"]},{"name":"var city: String? = null","description":"com.jumio.sdk.result.JumioIDResult.city","location":"jumio-core/com.jumio.sdk.result/-jumio-i-d-result/city.html","searchKeys":["city","var city: String? = null","com.jumio.sdk.result.JumioIDResult.city"]},{"name":"var country: String? = null","description":"com.jumio.sdk.result.JumioIDResult.country","location":"jumio-core/com.jumio.sdk.result/-jumio-i-d-result/country.html","searchKeys":["country","var country: String? = null","com.jumio.sdk.result.JumioIDResult.country"]},{"name":"var customThemeId: Int = 0","description":"com.jumio.sdk.JumioSDK.customThemeId","location":"jumio-core/com.jumio.sdk/-jumio-s-d-k/custom-theme-id.html","searchKeys":["customThemeId","var customThemeId: Int = 0","com.jumio.sdk.JumioSDK.customThemeId"]},{"name":"var dataCenter: JumioDataCenter? = null","description":"com.jumio.sdk.JumioSDK.dataCenter","location":"jumio-core/com.jumio.sdk/-jumio-s-d-k/data-center.html","searchKeys":["dataCenter","var dataCenter: JumioDataCenter? = null","com.jumio.sdk.JumioSDK.dataCenter"]},{"name":"var dateOfBirth: String? = null","description":"com.jumio.sdk.result.JumioIDResult.dateOfBirth","location":"jumio-core/com.jumio.sdk.result/-jumio-i-d-result/date-of-birth.html","searchKeys":["dateOfBirth","var dateOfBirth: String? = null","com.jumio.sdk.result.JumioIDResult.dateOfBirth"]},{"name":"var documentNumber: String? = null","description":"com.jumio.sdk.result.JumioIDResult.documentNumber","location":"jumio-core/com.jumio.sdk.result/-jumio-i-d-result/document-number.html","searchKeys":["documentNumber","var documentNumber: String? = null","com.jumio.sdk.result.JumioIDResult.documentNumber"]},{"name":"var expiryDate: String? = null","description":"com.jumio.sdk.result.JumioIDResult.expiryDate","location":"jumio-core/com.jumio.sdk.result/-jumio-i-d-result/expiry-date.html","searchKeys":["expiryDate","var expiryDate: String? = null","com.jumio.sdk.result.JumioIDResult.expiryDate"]},{"name":"var extractionMode: JumioScanMode? = null","description":"com.jumio.sdk.result.JumioCredentialResult.extractionMode","location":"jumio-core/com.jumio.sdk.result/-jumio-credential-result/extraction-mode.html","searchKeys":["extractionMode","var extractionMode: JumioScanMode? = null","com.jumio.sdk.result.JumioCredentialResult.extractionMode"]},{"name":"var firstName: String? = null","description":"com.jumio.sdk.result.JumioIDResult.firstName","location":"jumio-core/com.jumio.sdk.result/-jumio-i-d-result/first-name.html","searchKeys":["firstName","var firstName: String? = null","com.jumio.sdk.result.JumioIDResult.firstName"]},{"name":"var gender: String? = null","description":"com.jumio.sdk.result.JumioIDResult.gender","location":"jumio-core/com.jumio.sdk.result/-jumio-i-d-result/gender.html","searchKeys":["gender","var gender: String? = null","com.jumio.sdk.result.JumioIDResult.gender"]},{"name":"var idType: String? = null","description":"com.jumio.sdk.result.JumioIDResult.idType","location":"jumio-core/com.jumio.sdk.result/-jumio-i-d-result/id-type.html","searchKeys":["idType","var idType: String? = null","com.jumio.sdk.result.JumioIDResult.idType"]},{"name":"var imageData: JumioImageData? = null","description":"com.jumio.sdk.result.JumioCredentialResult.imageData","location":"jumio-core/com.jumio.sdk.result/-jumio-credential-result/image-data.html","searchKeys":["imageData","var imageData: JumioImageData? = null","com.jumio.sdk.result.JumioCredentialResult.imageData"]},{"name":"var issuingCountry: String? = null","description":"com.jumio.sdk.result.JumioIDResult.issuingCountry","location":"jumio-core/com.jumio.sdk.result/-jumio-i-d-result/issuing-country.html","searchKeys":["issuingCountry","var issuingCountry: String? = null","com.jumio.sdk.result.JumioIDResult.issuingCountry"]},{"name":"var issuingDate: String? = null","description":"com.jumio.sdk.result.JumioIDResult.issuingDate","location":"jumio-core/com.jumio.sdk.result/-jumio-i-d-result/issuing-date.html","searchKeys":["issuingDate","var issuingDate: String? = null","com.jumio.sdk.result.JumioIDResult.issuingDate"]},{"name":"var lastName: String? = null","description":"com.jumio.sdk.result.JumioIDResult.lastName","location":"jumio-core/com.jumio.sdk.result/-jumio-i-d-result/last-name.html","searchKeys":["lastName","var lastName: String? = null","com.jumio.sdk.result.JumioIDResult.lastName"]},{"name":"var mode: Int","description":"com.jumio.sdk.views.JumioScanView.mode","location":"jumio-core/com.jumio.sdk.views/-jumio-scan-view/mode.html","searchKeys":["mode","var mode: Int","com.jumio.sdk.views.JumioScanView.mode"]},{"name":"var mrzLine1: String? = null","description":"com.jumio.sdk.result.JumioIDResult.mrzLine1","location":"jumio-core/com.jumio.sdk.result/-jumio-i-d-result/mrz-line1.html","searchKeys":["mrzLine1","var mrzLine1: String? = null","com.jumio.sdk.result.JumioIDResult.mrzLine1"]},{"name":"var mrzLine2: String? = null","description":"com.jumio.sdk.result.JumioIDResult.mrzLine2","location":"jumio-core/com.jumio.sdk.result/-jumio-i-d-result/mrz-line2.html","searchKeys":["mrzLine2","var mrzLine2: String? = null","com.jumio.sdk.result.JumioIDResult.mrzLine2"]},{"name":"var mrzLine3: String? = null","description":"com.jumio.sdk.result.JumioIDResult.mrzLine3","location":"jumio-core/com.jumio.sdk.result/-jumio-i-d-result/mrz-line3.html","searchKeys":["mrzLine3","var mrzLine3: String? = null","com.jumio.sdk.result.JumioIDResult.mrzLine3"]},{"name":"var nationality: String? = null","description":"com.jumio.sdk.result.JumioIDResult.nationality","location":"jumio-core/com.jumio.sdk.result/-jumio-i-d-result/nationality.html","searchKeys":["nationality","var nationality: String? = null","com.jumio.sdk.result.JumioIDResult.nationality"]},{"name":"var passed: Boolean? = null","description":"com.jumio.sdk.result.JumioFaceResult.passed","location":"jumio-core/com.jumio.sdk.result/-jumio-face-result/passed.html","searchKeys":["passed","var passed: Boolean? = null","com.jumio.sdk.result.JumioFaceResult.passed"]},{"name":"var personalNumber: String? = null","description":"com.jumio.sdk.result.JumioIDResult.personalNumber","location":"jumio-core/com.jumio.sdk.result/-jumio-i-d-result/personal-number.html","searchKeys":["personalNumber","var personalNumber: String? = null","com.jumio.sdk.result.JumioIDResult.personalNumber"]},{"name":"var placeOfBirth: String? = null","description":"com.jumio.sdk.result.JumioIDResult.placeOfBirth","location":"jumio-core/com.jumio.sdk.result/-jumio-i-d-result/place-of-birth.html","searchKeys":["placeOfBirth","var placeOfBirth: String? = null","com.jumio.sdk.result.JumioIDResult.placeOfBirth"]},{"name":"var postalCode: String? = null","description":"com.jumio.sdk.result.JumioIDResult.postalCode","location":"jumio-core/com.jumio.sdk.result/-jumio-i-d-result/postal-code.html","searchKeys":["postalCode","var postalCode: String? = null","com.jumio.sdk.result.JumioIDResult.postalCode"]},{"name":"var rawBarcodeData: String? = null","description":"com.jumio.sdk.result.JumioIDResult.rawBarcodeData","location":"jumio-core/com.jumio.sdk.result/-jumio-i-d-result/raw-barcode-data.html","searchKeys":["rawBarcodeData","var rawBarcodeData: String? = null","com.jumio.sdk.result.JumioIDResult.rawBarcodeData"]},{"name":"var subdivision: String? = null","description":"com.jumio.sdk.result.JumioIDResult.subdivision","location":"jumio-core/com.jumio.sdk.result/-jumio-i-d-result/subdivision.html","searchKeys":["subdivision","var subdivision: String? = null","com.jumio.sdk.result.JumioIDResult.subdivision"]},{"name":"var token: String","description":"com.jumio.sdk.JumioSDK.token","location":"jumio-core/com.jumio.sdk/-jumio-s-d-k/token.html","searchKeys":["token","var token: String","com.jumio.sdk.JumioSDK.token"]}]